Workbook

Sheet All Subcamps
A1: No | B1: First name | C1: Last name | D1: Email | E1: Mobile phone | F1: Invoice details | G1: Country | H1: Scout Association | I1: Troop name | J1: Troop organisation number | K1: City | L1: Number of Children | M1: Number of Leaders | N1: Arrival day | O1: Arrival time | P1: Departure day | Q1: Departure time | R1: Further remarks (optional) | S1: Order Number | T1: Total Costs | U1: Payment Type | V1: Registration time | W1: Order Number2 | X1: Additional registrants | Y1: Comments RJ: | Z1: Subcamp
A2: 33 | B2: Joseph | C2: Monk | D2: joe.monk@britishscoutingoverseas.org.uk | E2: +32484266960 | G2: Belgium | H2: FOS Open Scouting | I2: Central Brussels Scouts | J2: 112e | K2: Brussels | L2: 15 | M2: 5 | N2: Friday | O2: 21:00 - 00:00 | P2: Monday | Q2: 15:00 - 18:00 | R2: Arrival and Departure times are estimates. 2 additional Scouters needed due to logistical requirements to transport youth and equipment. | S2: IST-18979 | T2: 500 | U2: Mollie | V2: 2024-12-02 09:42:04 | W2: 1733132524 | Z2: 2
A3: 30 | B3: Jonathan | C3: Copner | D3: jon.copner@britishscoutingoverseas.org.uk | E3: +32 | F3: Grootveldlaan 12, 3080 Tervuren, Belgium | G3: Belgium | H3: FOS Open Scouting | I3: Brussels Explorers | J3: FOS111 | K3: Tervuren | L3: 12 | M3: 3 | N3: Friday | O3: 18:00 - 21:00 | P3: Monday | Q3: 12:00 - 15:00 | R3: 3 leaders - 3 vehicles required | S3: IST-95976 | T3: 375 | U3: Mollie | V3: 2024-12-01 12:56:03 | W3: 1733057763 | Z3: 2
A4: 59 | B4: Barbora | C4: Jánská | D4: janskabarbora@gmail.com | E4: +420733650318 | G4: Czech Republic | H4: JUNAK - cesky skaut | I4: Dráčata Štěnovice | J4: 323.02 | K4: Štěnovice | L4: 20 | M4: 4 | N4: Friday | O4: 18:00 - 21:00 | P4: Monday | Q4: 09:00 - 12:00 | S4: IST-69112 | T4: 600 | U4: Mollie | V4: 2025-01-13 14:28:34 | W4: 1736778514 | Z4: 1
A5: 60 | B5: Martin | C5: Kolarik | D5: smurf@skaut.cz | E5: +420723923943 | F5: Junák – český skaut, středisko Járy Kaštila Prostějov, z. s. Sokolská 30, 796 01 Prostějov Czech republic IČO: 65762959 | G5: Czech Republic | H5: JUNAK - cesky skaut | I5: JK | J5: 713.05 | K5: Prostejov | L5: 20 | M5: 4 | N5: Friday | O5: 15:00 - 18:00 | P5: Monday | Q5: 09:00 - 12:00 | S5: IST-11762 | T5: 600 | U5: Mollie | V5: 2025-01-15 07:08:46 | W5: 1736924926 | Z5: 3
A6: 61 | B6: Pavel | C6: Šenkyřík | D6: 180.veneta@gmail.com | E6: +420733233486 | F6: Customer: Junák - český skaut, středisko Platan Praha, z. s. Adress: Viktorinova 1122/1,Praha 4 – Nusle, 140 00 Praha, Česká Republika IČO: 40613593 | G6: Czech Republic | H6: JUNAK - cesky skaut | I6: Platan | J6: 114.32 | K6: Prague | L6: 20 | M6: 3 | N6: Friday | O6: 18:00 - 21:00 | P6: Monday | Q6: 09:00 - 12:00 | S6: IST-32540 | T6: 575 | U6: Mollie | V6: 2025-01-18 14:39:42 | W6: 1737211182 | Z6: 3
A7: 62 | B7: Lenka | C7: Hechtová | D7: lenkalischkova@gmail.com | E7: +420607881402 | G7: Czech Republic | H7: JUNAK - cesky skaut | I7: Core | J7: 511.02.004 | K7: Nový Bor | L7: 20 | M7: 4 | N7: Friday | O7: 18:00 - 21:00 | P7: Monday | Q7: 09:00 - 12:00 | S7: IST-18688 | T7: 600 | U7: Mollie | V7: 2025-01-19 18:16:07 | W7: 1737310567 | Z7: 2
A8: 63 | B8: Petr | C8: Kvarda | D8: kvardic.p@seznam.cz | E8: +420739528720 | G8: Czech Republic | H8: JUNAK - cesky skaut | I8: Goliath | J8: 611.05 | K8: Přibyslav | L8: 8 | M8: 2 | N8: Friday | O8: 12:00 - 15:00 | P8: Monday | Q8: 15:00 - 18:00 | S8: IST-12285 | T8: 250 | U8: Mollie | V8: 2025-01-20 17:26:18 | W8: 1737393978 | Z8: 2
A9: 64 | B9: Klára | C9: Helánová | D9: akela.sebetov@skaut.cz | E9: +420777865883 | F9: Junák - Český skaut, středisko Severka, z.s. Šebetov 49 679 35 Czech Republic | G9: Czech Republic | H9: JUNAK - cesky skaut | I9: Středisko Severka | J9: 621.11 | K9: Šebetov | L9: 15 | M9: 3 | N9: Friday | O9: 15:00 - 18:00 | P9: Monday | Q9: 12:00 - 15:00 | R9: We are not sure about the arrival time yet. We're in the process of deciding between Friday morning (around 10 am) and evening (around 6 pm). We'll let you know once we've settled. | S9: IST-64335 | T9: 450 | U9: Mollie | V9: 2025-01-21 17:35:18 | W9: 1737480918 | Z9: 2
A10: 65 | B10: Jan | C10: Holoubek | D10: jan.holoubek@skaut.cz | E10: +420736149229 | G10: Czech Republic | H10: JUNAK - cesky skaut | I10: Stopa | J10: 526.06.004 | K10: Hradec Králové | L10: 6 | M10: 2 | N10: Friday | O10: 12:00 - 15:00 | P10: Monday | Q10: 09:00 - 12:00 | R10: We need to be two adults for safety reasons (two drivers). Also we both work with the troop during the year as mentors. | S10: IST-54674 | T10: 200 | U10: Mollie | V10: 2025-01-22 16:15:01 | W10: 1737562501 | Z10: 1
A11: 66 | B11: Vojtěch | C11: Podzimek | D11: podzimek.vojta@skaut.cz | E11: +420724144345 | F11: Junák - český skaut, středisko Sopka Nová Paka, z. s. Svatojánská 1193 509 01 Nová Paka IČ: 60116421 | G11: Czech Republic | H11: JUNAK - cesky skaut | I11: Sopka Nová Paka | J11: 522.03 | K11: NOVÁ PAKA | L11: 20 | M11: 4 | N11: Friday | O11: 18:00 - 21:00 | P11: Monday | Q11: 09:00 - 12:00 | S11: IST-16688 | T11: 600 | U11: Mollie | V11: 2025-01-22 20:56:18 | W11: 1737579378 | Z11: 1
A12: 67 | B12: Šimon | C12: Trousil | D12: simon.trousil@seznam.cz | E12: +420720103492 | G12: Czech Republic | H12: JUNAK - cesky skaut | I12: Orion Kladno | J12: 213.01 | K12: Kladno | L12: 18 | M12: 3 | N12: Friday | O12: 15:00 - 18:00 | P12: Monday | Q12: 09:00 - 12:00 | R12: We are traveling from the Czech Republic by bus together with another group of scouts and we are currently planning the bus, so we don't know the exact time of arrival. | S12: IST-92152 | T12: 525 | U12: Mollie | V12: 2025-01-24 10:58:50 | W12: 1737716330 | Z12: 4
A13: 70 | B13: Dana | C13: Tarantová | D13: komtesa.dana@gmail.com | E13: +420606227817 | F13: Junák - český skaut, středisko Oheň Most, z. s. Slovenského národního povstání 1191 434 01 Most IČ: 41324919 | G13: Czech Republic | H13: JUNAK - cesky skaut | I13: Junák - český skaut, středisko Oheň Most, z. s. | J13: 42501 | K13: Most | L13: 20 | M13: 4 | N13: Friday | O13: 15:00 - 18:00 | P13: Monday | Q13: 09:00 - 12:00 | S13: IST-15385 | T13: 600 | U13: Mollie | V13: 2025-01-26 18:36:08 | W13: 1737916569 | Z13: 3
A14: 71 | B14: Ondřej | C14: Mikulčík | D14: ondrej.mikulcik@gmail.com | E14: +420702282329 | F14: Junák Český skaut - středisko Vizovice z.s. Razov 761 Vizovice 76312 Czech republic IC: 46277404 | G14: Czech Republic | H14: JUNAK - cesky skaut | I14: Vizovice | J14: 724.12 | K14: Vizovice | L14: 13 | M14: 2 | N14: Friday | O14: 09:00 - 12:00 | P14: Monday | Q14: 09:00 - 12:00 | S14: IST-29006 | T14: 375 | U14: Mollie | V14: 2025-01-28 16:33:49 | W14: 1738082029 | Z14: 3
A15: 72 | B15: Vanda | C15: Hegerová | D15: vanda.hegerova@seznam.cz | E15: +420 | G15: Czech Republic | H15: JUNAK - cesky skaut | I15: Blaník | J15: 114.07 | K15: Prague | L15: 4 | M15: 1 | N15: Friday | O15: 15:00 - 18:00 | P15: Monday | Q15: 09:00 - 12:00 | R15: Arrival time is not exactly we are still planing. | S15: IST-81258 | T15: 125 | U15: Mollie | V15: 2025-01-28 19:14:48 | W15: 1738091688 | Z15: 4
A16: 73 | B16: Jonáš | C16: Novotný | D16: novotny.jonas@seznam.cz | E16: +420731403977 | G16: Czech Republic | H16: JUNAK - cesky skaut | I16: Anikrok a Dvojka | J16: 532.08 | K16: Přelouč | L16: 14 | M16: 4 | N16: Friday | O16: 12:00 - 15:00 | P16: Monday | Q16: 09:00 - 12:00 | S16: IST-95252 | T16: 450 | U16: Mollie | V16: 2025-01-28 19:30:24 | W16: 1738092624 | Z16: 3
A17: 75 | B17: Agáta | C17: Navrkalová | D17: agata.nvr@skaut.cz | E17: +420773301941 | G17: Czech Republic | H17: JUNAK - cesky skaut | I17: Junák - český skaut, středisko Podyjí Znojmo, z. s. | J17: 627.02 | K17: Znojmo | L17: 8 | M17: 2 | N17: Friday | O17: 09:00 - 12:00 | P17: Monday | Q17: 12:00 - 15:00 | S17: IST-18787 | T17: 250 | U17: Mollie | V17: 2025-01-31 10:36:55 | W17: 1738319816 | Z17: 3
A18: 76 | B18: Vlastimil | C18: Buriánek | D18: vlastimil.burianek@skaut.cz | E18: +420725561858 | G18: Czech Republic | H18: JUNAK - cesky skaut | I18: Děti přírody | J18: 713.02 | K18: Prostějov | L18: 9 | M18: 2 | N18: Friday | O18: 15:00 - 18:00 | P18: Monday | Q18: 12:00 - 15:00 | R18: Departure/arrival times are (still) approximate. | S18: IST-20023 | T18: 275 | U18: Mollie | V18: 2025-01-31 20:17:50 | W18: 1738354670 | Z18: 4
A19: 77 | B19: Ondřej | C19: Rejsek | D19: ondrej.rejsek@seznam.cz | E19: +420605211206 | F19: Junák - český skaut, středisko Želivák Hradec Králové, z. s. Čajkovského 1861/46A, 500 09 Hradec Králové IČO: 62693158 | G19: Czech Republic | H19: JUNAK - cesky skaut | I19: Želivák | J19: 526.07 | K19: Hradec Králové | L19: 12 | M19: 3 | N19: Friday | O19: 09:00 - 12:00 | P19: Monday | Q19: 09:00 - 12:00 | R19: We have exceeded the participant rate, because two of the leaders are still rangers in the age of 18, which want to go together. We would like to give them the opportunity to gain experience in leadership - to participate in organization of the international event. In our opinion they should have the support of older and experienced leader. Unfortunately the number of scout - participants is a little bit lower than expected. | S19: IST-64944 | T19: 375 | U19: Mollie | V19: 2025-01-31 20:55:09 | W19: 1738356909 | Z19: 2
A20: 78 | B20: Antonín | C20: Kala | D20: tonda.kala@seznam.cz | E20: +420603472473 | G20: Czech Republic | H20: JUNAK - cesky skaut | I20: Stopaři | J20: 118.52 | K20: Praha | L20: 14 | M20: 2 | N20: Friday | O20: 15:00 - 18:00 | P20: Monday | Q20: 12:00 - 15:00 | S20: IST-19283 | T20: 400 | U20: Mollie | V20: 2025-01-31 22:47:55 | W20: 1738363675 | Z20: 2
A21: 80 | B21: Jiří | C21: Granát | D21: namornik@skaut.cz | E21: +420732310218 | G21: Czech Republic | H21: JUNAK - cesky skaut | I21: Junák Kostelec nad Orlicí | J21: 524.03 | K21: Kostelec nad Orlicí | L21: 20 | M21: 4 | N21: Friday | O21: 09:00 - 12:00 | P21: Monday | Q21: 09:00 - 12:00 | S21: IST-23514 | T21: 600 | U21: Mollie | V21: 2025-02-01 21:53:16 | W21: 1738446796 | Z21: 2
A22: 82 | B22: Lucie | C22: Urbanová | D22: lucie.urbn@gmail.com | E22: +420728900846 | G22: Czech Republic | H22: JUNAK - cesky skaut | I22: Devítky | J22: 533.02 | K22: Litomyšl | L22: 8 | M22: 1 | N22: Friday | O22: 12:00 - 15:00 | P22: Monday | Q22: 12:00 - 15:00 | S22: IST-66761 | T22: 225 | U22: Mollie | V22: 2025-02-03 15:13:33 | W22: 1738595613 | Z22: 4
A23: 83 | B23: Kateřina | C23: Tuháčková | D23: katy58@skaut.cz | E23: +420725882920 | G23: Czech Republic | H23: JUNAK - cesky skaut | I23: Sluneční údolí | J23: 323.05.058 | K23: Starý Plzenec | L23: 8 | M23: 1 | N23: Friday | O23: 15:00 - 18:00 | P23: Monday | Q23: 09:00 - 12:00 | S23: IST-11470 | T23: 225 | U23: Mollie | V23: 2025-02-03 20:18:05 | W23: 1738613885 | Z23: 3
A24: 85 | B24: Jiří | C24: Nevřivý | D24: nevrivy.skaut@gmail.com | E24: +420736678622 | G24: Czech Republic | H24: JUNAK - cesky skaut | I24: Artemis/Ontario | J24: 724.06 | K24: Zlín-Malenovice | L24: 20 | M24: 4 | N24: Friday | O24: 15:00 - 18:00 | P24: Monday | Q24: 09:00 - 12:00 | S24: IST-97908 | T24: 600 | U24: Mollie | V24: 2025-02-04 22:26:15 | W24: 1738707976 | Z24: 4
A25: 100 | B25: Filip | C25: Fišer | D25: fiser-filip@seznam.cz | E25: +420731993016 | F25: Junák - český skaut, středisko Vamberk, z. s. Ič.: 42885311 V Lukách 598, 517 54 Vamberk | G25: Czech Republic | H25: JUNAK - cesky skaut | I25: 2. Oddíl (DSS) | J25: 524.09.002 | K25: Vamberk | L25: 6 | M25: 2 | N25: Friday | O25: 09:00 - 12:00 | P25: Monday | Q25: 09:00 - 12:00 | R25: the second leader Jaroslav Vašátko +420 733 580 760 jaroslav.vasatko@seznam.cz | S25: IST-21179 | T25: 200 | U25: Mollie | V25: 2025-02-07 14:42:26 | W25: 1738939346 | Z25: 1
A26: 101 | B26: Martin | C26: Matyáš | D26: matyasmartin0@gmail.com | E26: +420608642615 | G26: Czech Republic | H26: JUNAK - cesky skaut | I26: Tumulus Újezd u Brna aneb děcka, pecka, pojedeme do Německa | J26: 623.14 | K26: Újezd u Brna | L26: 5 | M26: 1 | N26: Friday | O26: 15:00 - 18:00 | P26: Monday | Q26: 12:00 - 15:00 | S26: IST-30049 | T26: 150 | U26: Mollie | V26: 2025-02-09 18:29:12 | W26: 1739125752 | Z26: 4
A27: 103 | B27: Bára | C27: Matoušová | D27: matousova.bara@skaut.cz | E27: +420605989853 | G27: Czech Republic | H27: JUNAK - cesky skaut | I27: Fata Morgana | J27: 523.1 | K27: Nové Město nad Metují | L27: 5 | M27: 1 | N27: Friday | O27: 09:00 - 12:00 | P27: Monday | Q27: 12:00 - 15:00 | S27: IST-64369 | T27: 150 | U27: Mollie | V27: 2025-02-10 13:55:50 | W27: 1739195751 | Z27: 2
A28: 104 | B28: Pavel | C28: Čechura | D28: pavelcechura@seznam.cz | E28: +420607927028 | G28: Czech Republic | H28: JUNAK - cesky skaut | I28: Třebechovice | J28: 521.01 | K28: Třebechovice pod Orebem | L28: 20 | M28: 4 | N28: Friday | O28: 09:00 - 12:00 | P28: Monday | Q28: 09:00 - 12:00 | S28: IST-84861 | T28: 600 | U28: Mollie | V28: 2025-02-10 16:39:41 | W28: 1739205581 | Z28: 2
A29: 105 | B29: Kateřina | C29: Čechová | D29: albus@skaut.cz | E29: +420602144407 | F29: Junák – český skaut, středisko Bílý los Praha, z. s. , Praha Liborova 470/2, Praha 6 – Břevnov, 16900 IČ: 61389650 | G29: Czech Republic | H29: JUNAK - cesky skaut | I29: Bílý los | J29: 116.33 | K29: Prague | L29: 6 | M29: 1 | N29: Friday | O29: 15:00 - 18:00 | P29: Monday | Q29: 12:00 - 15:00 | R29: Hello, we are not sure about out arrival and departure time, but I think we will be flexible about that. We are going to order bus with another few troops form our area. Greets, Katka Čechová - Albus. | S29: IST-15861 | T29: 175 | U29: Mollie | V29: 2025-02-10 18:13:21 | W29: 1739211201 | Z29: 3
A30: 106 | B30: Miroslav | C30: Král | D30: usteckadvojka@gmail.com | E30: +420605567227 | G30: Czech Republic | H30: JUNAK - cesky skaut | I30: Ústecká dvojka | J30: 427.01.002 | K30: Ústí nad Labem | L30: 20 | M30: 4 | N30: Friday | O30: 15:00 - 18:00 | P30: Monday | Q30: 09:00 - 12:00 | S30: IST-21250 | T30: 600 | U30: Mollie | V30: 2025-02-11 16:48:31 | W30: 1739292511 | Z30: 3
A31: 112 | B31: Michal | C31: Sýkora | D31: sykoramichal@skaut.cz | E31: +420739102827 | G31: Czech Republic | H31: JUNAK - cesky skaut | I31: AD FONTES | J31: 621.08 | K31: Šebrov - Kateřina | L31: 20 | M31: 4 | N31: Friday | O31: 09:00 - 12:00 | P31: Monday | Q31: 09:00 - 12:00 | S31: IST-54943 | T31: 600 | U31: Mollie | V31: 2025-02-17 21:05:42 | W31: 1739826342 | Z31: 2
A32: 127 | B32: Marie Anna | C32: Chlachulová | D32: mchlachulov.a@seznam.cz | E32: +420773883110 | G32: Czech Republic | H32: JUNAK - cesky skaut | I32: Mustangové | J32: 722.01 | K32: Uherské Hradiště | L32: 8 | M32: 2 | N32: Friday | O32: 15:00 - 18:00 | P32: Monday | Q32: 09:00 - 12:00 | R32: We have 2 leaders And 8 children, since we have both just turned 18 And we have no previous experience travelling with kids alone, we think it will be more responsible and safer to travel abroad with the kids with 2 leaders . | S32: IST-81116 | T32: 250 | U32: Mollie | V32: 2025-03-04 16:42:05 | W32: 1741106525 | Z32: 4
A33: 130 | B33: Mikuláš | C33: Jandík | D33: jandik.mikulasz@gmail.com | E33: +420731743330 | F33: Junák - český skaut, Středisko bratří Mašínů Praha z. s., Čihákova 1791/20, Praha 9, 190 00 | G33: Czech Republic | H33: JUNAK - cesky skaut | I33: Ginkgo | J33: 112.53 | K33: Praha | L33: 13 | M33: 2 | N33: Friday | O33: 18:00 - 21:00 | P33: Monday | Q33: 09:00 - 12:00 | R33: It is possible that we will arrive at a different time (during Friday afternoon or evening). | S33: IST-18827 | T33: 375 | U33: Mollie | V33: 2025-03-20 17:00:41 | W33: 1742490041 | Z33: 3
A34: 42 | B34: Lynn | C34: Millard | D34: lynn.millard@britishscoutingoverseas.org.uk | E34: +33637844303 | G34: GB | H34: BSO | I34: 1st Maisons-Laffitte International | J34: lynn burns nutrition | K34: Maisons-Laffitte | L34: 10 | M34: 3 | N34: Friday | O34: 21:00 - 00:00 | P34: Monday | Q34: 12:00 - 15:00 | R34: Partnering with 1st Prague Scouts as we are sharing equipment - Added extra leader but if not needed will let you know. We have potential requirement for additional adult for neurodivergent kids/support driving. Rather book one extra and cancel than the other way around. | S34: IST-11256 | T34: 325 | U34: Mollie | V34: 2024-12-04 19:36:32 | W34: 1733340992 | Z34: 2
A35: 57 | B35: Ulrich | C35: Maurach | D35: mail@ulrich-maurach.de | E35: +491713141429 | F35: Team! I’m a german father (born in HH) of a 14 year old daughter and made my promise as a British Scout in Celle, Lower Saxony (Niedersachsen) during the 80’s. A became a Venture Scout during that time and attended only one Intercamp – must have been near the river Rhine close to Bernkastel-Kues. This year I would like to attend the Intercamp, to show my daughter, what a wonderful movement scouting is. I do offer being a ‘helper’ during the event where ever it is needed. So – is it possible to attend with 1 tent and two persons? I hope to hear from you - Ulrich Ulrich Maurach M +49171 3141429 mail@ulrich-maurach.de | G35: GB | H35: BSO | I35: Ulrich Maurach | J35: -/- | K35: Berlin | L35: 1 | M35: 1 | N35: Friday | O35: 15:00 - 18:00 | P35: Monday | Q35: 12:00 - 15:00 | R35: Team! I’m a german father (born in HH) of a 14 year old daughter and made my promise as a British Scout in Celle, Lower Saxony (Niedersachsen) during the 80’s. A became a Venture Scout during that time and attended only one Intercamp – must have been near the river Rhine close to Bernkastel-Kues. This year I would like to attend the Intercamp, to show my daughter, what a wonderful movement scouting is. I do offer being a ‘helper’ during the event where ever it is needed. So – is it possible to attend with 1 tent and two persons? I hope to hear from you - Ulrich Ulrich Maurach M +49171 3141429 mail@ulrich-maurach.de | S35: IST-45306 | T35: 50 | U35: Mollie | V35: 2025-01-09 08:35:01 | W35: 1736411701 | Z35: 1
A36: 58 | B36: POGGIO | C36: STEPHAN | D36: poggio.stephan@yahoo.com | E36: +33632153653 | G36: France | H36: Scoutisme Français | I36: Scout du Florival | J36: EEDF - GUEBWILLER - SCOUTS DU FLORIVAL - 706019 | K36: Guebwiller - Soultz | L36: 21 | M36: 4 | N36: Friday | O36: 12:00 - 15:00 | P36: Monday | Q36: 09:00 - 12:00 | S36: IST-13515 | T36: 625 | U36: Mollie | V36: 2025-01-12 17:15:12 | W36: 1736702112 | Z36: 3
A37: 19 | B37: Caroline | C37: Pintsch | D37: caroline@pintsch.de | E37: +4915786783461 | G37: Germany | H37: Deutsche Pfadfinderschaft Sankt Georg | I37: DPSG Stamm Alzenau | J37: 2020329 | K37: Alzenau | L37: 17 | M37: 4 | N37: Friday | O37: 15:00 - 18:00 | P37: Monday | Q37: 12:00 - 15:00 | S37: IST-23477 | T37: 525 | U37: Mollie | V37: 2024-11-30 23:13:25 | W37: 1733008405 | Z37: 4
A38: 20 | B38: Jonas | C38: Spinczyk | D38: Jonas.spinczyk@rdp-bund.de | E38: +491621979714 | G38: Germany | H38: Deutsche Pfadfinderschaft Sankt Georg | I38: DPSG Kempen | J38: 01/02/12 | K38: Kempen | L38: 21 | M38: 5 | N38: Friday | O38: 15:00 - 18:00 | P38: Monday | Q38: 09:00 - 12:00 | R38: We need one more scout leader, because of a disabled participant. | S38: IST-11133 | T38: 650 | U38: Mollie | V38: 2024-11-30 23:17:00 | W38: 1733008620 | Z38: 2
A39: 22 | B39: Robin | C39: Bandini | D39: vorstand@pfadfinder-bammental.de | E39: +491627911091 | G39: Germany | H39: Deutsche Pfadfinderschaft Sankt Georg | I39: Stamm Karl Leisner | J39: 3363 | K39: Bammental | L39: 14 | M39: 3 | N39: Friday | O39: 18:00 - 21:00 | P39: Monday | Q39: 12:00 - 15:00 | S39: IST-11133 | T39: 425 | U39: Mollie | V39: 2024-11-30 23:33:26 | W39: 1733009606 | Z39: 1
A40: 23 | B40: Sebastian | C40: Kiwitt | D40: s-kiwitt@outlook.de | E40: +4917622228294 | F40: Sebastian Kiwitt DPSG Stamm St. Viktor Xanten Schwarzer Weg 10 46509 Xanten | G40: Germany | H40: Deutsche Pfadfinderschaft Sankt Georg | I40: DPSG Stamm St. Viktor Xanten | J40: 140101 | K40: Xanten | L40: 27 | M40: 7 | N40: Friday | O40: 12:00 - 15:00 | P40: Monday | Q40: 12:00 - 15:00 | R40: We need more Leeders, because we come with two Leeder by Car and the others with the Kids by Train. And I think Four Leeders with 27 Kids is not so safety. I hope this is Ok for you. Thank you. Best regards Sebastian | S40: IST-11133 | T40: 850 | U40: Mollie | V40: 2024-11-30 23:36:13 | W40: 1733009773 | Z40: 2
A41: 24 | B41: Martin | C41: Babst | D41: martin.babst@web.de | E41: +4915126957577 | G41: Germany | H41: Deutsche Pfadfinderschaft Sankt Georg | I41: Maximilan Kolbe Lammersdorf | J41: 010607 | K41: Aachen | L41: 48 | M41: 9 | N41: Friday | O41: 12:00 - 15:00 | P41: Monday | Q41: 12:00 - 15:00 | S41: IST-11133 | T41: 1425 | U41: Mollie | V41: 2024-12-01 00:20:50 | W41: 1733012451 | Z41: 1
A42: 25 | B42: Daniela | C42: Kouril | D42: daniela@cityscouts.org | E42: +491605807584 | F42: Falls Julia vom Dorp dieses Jahr in einem Subcampteam ist, möchten wir gerne in ihr Subcamp. Sie ist Leiterin in unserem Stamm. | G42: Germany | H42: Deutsche Pfadfinderschaft Sankt Georg | I42: Stamm Cityscouts | J42: 010304 | K42: Mönchengladbach | L42: 27 | M42: 6 | N42: Friday | O42: 12:00 - 15:00 | P42: Monday | Q42: 12:00 - 15:00 | S42: IST-11133 | T42: 825 | U42: Mollie | V42: 2024-12-01 00:21:33 | W42: 1733012493 | Z42: 3
A43: 26 | B43: Jan | C43: Van den Brakel | D43: jbrl@cbs.nl | E43: +31 | F43: I will pay via banktransfer. | G43: Germany | H43: Deutsche Pfadfinderschaft Sankt Georg | I43: St Nikolaus Gangelt | J43: 010403 | K43: Gangelt | L43: 12 | M43: 4 | N43: Friday | O43: 12:00 - 15:00 | P43: Monday | Q43: 12:00 - 15:00 | R43: WE need four leaders for transportation. | S43: IST-41645 | T43: 400 | U43: Mollie | V43: 2024-12-01 09:32:32 | W43: 1733045552 | Z43: 3
A44: 28 | B44: Katharina | C44: Wenderott | D44: k.wenderott@paderborn.com | E44: +4915750634181 | F44: Pastoralbüro An St. Marien DPSG Phönix Bonn Heerstraße 128 53111 Bonn lea@dpsg-phoenix.net | G44: Germany | H44: Deutsche Pfadfinderschaft Sankt Georg | I44: DPSG Phönix Bonn | J44: 10/12/03 | K44: Bonn | L44: 26 | M44: 6 | N44: Friday | O44: 18:00 - 21:00 | P44: Monday | Q44: 09:00 - 12:00 | S44: IST-13423 | T44: 800 | U44: Mollie | V44: 2024-12-01 12:09:38 | W44: 1733054978 | Z44: 3
A45: 29 | B45: Sarah | C45: Corres | D45: corres.sarah@gmx.de | E45: +491754170858 | G45: Germany | H45: Deutsche Pfadfinderschaft Sankt Georg | I45: Pfadfinder Erkelenz | J45: 010413 | K45: Erkelenz | L45: 25 | M45: 5 | N45: Friday | O45: 15:00 - 18:00 | P45: Monday | Q45: 09:00 - 12:00 | S45: IST-17411 | T45: 750 | U45: Mollie | V45: 2024-12-01 12:15:33 | W45: 1733055333 | Z45: 3
A46: 34 | B46: Svenja | C46: Walter | D46: svenjawalter95@web.de | E46: +491741021155 | G46: Germany | H46: Deutsche Pfadfinderschaft Sankt Georg | I46: DPSG Obertürkheim Stamm St. Franziskus | J46: 19/01/01 | K46: Stuttgart | L46: 5 | M46: 3 | N46: Friday | O46: 12:00 - 15:00 | P46: Monday | Q46: 12:00 - 15:00 | S46: IST-10640 | T46: 200 | U46: Mollie | V46: 2024-12-02 10:28:28 | W46: 1733135308 | Z46: 3
A47: 35 | B47: Lale | C47: Akman | D47: laleakman@yahoo.de | E47: +4917684098636 | F47: Eichendorffstraße 8, 68167 Mannheim | G47: Germany | H47: Deutsche Pfadfinderschaft Sankt Georg | I47: St. Bernhard | J47: 070101 | K47: Mannheim | L47: 15 | M47: 4 | N47: Friday | O47: 12:00 - 15:00 | P47: Monday | Q47: 15:00 - 18:00 | S47: IST-17058 | T47: 475 | U47: Mollie | V47: 2024-12-02 18:01:18 | W47: 1733162478 | Z47: 2
A48: 36 | B48: Fabian | C48: Berger | D48: bigberger@gmx.de | E48: +4917620771317 | G48: Germany | H48: Deutsche Pfadfinderschaft Sankt Georg | I48: DPSG Stamm Cherusker | J48: 0007010300 | K48: Laudenbach | L48: 13 | M48: 2 | N48: Friday | O48: 15:00 - 18:00 | P48: Monday | Q48: 12:00 - 15:00 | S48: IST-18820 | T48: 375 | U48: Mollie | V48: 2024-12-02 18:30:47 | W48: 1733164247 | Z48: 2
A49: 37 | B49: Malte | C49: Grönemann | D49: malte.groenemann@dpsg-friedrichsfeld.de | E49: +4917641629411 | G49: Germany | H49: Deutsche Pfadfinderschaft Sankt Georg | I49: DPSG St. Bonifatius Mannheim | J49: 070106 | K49: Mannheim | L49: 9 | M49: 2 | N49: Friday | O49: 18:00 - 21:00 | P49: Monday | Q49: 12:00 - 15:00 | S49: IST-96584 | T49: 200 | U49: Mollie | V49: 2024-12-02 18:49:22 | W49: 1733165362 | Y49: add. 3 kids | Z49: 2
A50: 38 | B50: Sven | C50: Mühlen | D50: sven@dpsgwegberg.de | E50: +4917696819125 | F50: DPSG Wegberg | G50: Germany | H50: Deutsche Pfadfinderschaft Sankt Georg | I50: DPSG Wegberg | J50: 0001041000 | K50: Wegberg | L50: 30 | M50: 6 | N50: Friday | O50: 18:00 - 21:00 | P50: Monday | Q50: 09:00 - 12:00 | S50: IST-46593 | T50: 900 | U50: Mollie | V50: 2024-12-02 20:03:36 | W50: 1733169816 | Z50: 2
A51: 39 | B51: Fabian | C51: Dietzmann | D51: fabian.dietzmann@gmail.com | E51: +4917643431461 | G51: Germany | H51: Deutsche Pfadfinderschaft Sankt Georg | I51: Stamm von Berg | J51: 0010010100 | K51: Solingen | L51: 22 | M51: 5 | N51: Friday | O51: 15:00 - 18:00 | P51: Monday | Q51: 09:00 - 12:00 | S51: IST-31582 | T51: 675 | U51: Mollie | V51: 2024-12-02 21:07:13 | W51: 1733173633 | Z51: 3
A52: 40 | B52: Anna-Maria | C52: Aggelakos | D52: anna.aggelakos@hotmail.de | E52: +491722940241 | F52: Empfänger: Freundes- u. Förderverein des Stammes Sr. Felicitas HD-Zgh e.V. IBAN: DE28 6709 2300 0033 1350 92 BIC: GENODE61WNM Bank: Volksbank Kurpfalz eG | G52: Germany | H52: Deutsche Pfadfinderschaft Sankt Georg | I52: Stamm Schwester Felicitas Ziegelhausen | J52: DPSG Schwester Felicitas Ziegelhausen | K52: Heidelberg | L52: 12 | M52: 3 | N52: Friday | O52: 15:00 - 18:00 | P52: Monday | Q52: 12:00 - 15:00 | S52: IST-12782 | T52: 375 | U52: Mollie | V52: 2024-12-02 22:20:06 | W52: 1733178006 | Z52: 4
A53: 41 | B53: Wolfgang | C53: Otto | D53: scouterwolfgang@aol.com | E53: +4915753131324 | G53: Germany | H53: Deutsche Pfadfinderschaft Sankt Georg | I53: DPSG Moers St. Josef | J53: 14/08/01 | K53: Moers | L53: 5 | M53: 1 | N53: Friday | O53: 18:00 - 21:00 | P53: Monday | Q53: 09:00 - 12:00 | S53: IST-80873 | T53: 150 | U53: Mollie | V53: 2024-12-03 22:28:03 | W53: 1733264883 | Z53: 4
A54: 45 | B54: Robert | C54: Birkmann | D54: robert.birkmann@ostgoten.de | E54: +4915151277360 | G54: Germany | H54: Deutsche Pfadfinderschaft Sankt Georg | I54: Stamm Ostgoten/Rheinbezirk | J54: 010107 | K54: Krefeld | L54: 21 | M54: 5 | N54: Friday | O54: 09:00 - 12:00 | P54: Monday | Q54: 09:00 - 12:00 | S54: IST-12385 | T54: 650 | U54: Mollie | V54: 2024-12-07 20:10:04 | W54: 1733602204 | Z54: 4
A55: 46 | B55: Annika | C55: Tobies | D55: an@tobies.info | E55: +4915734650329 | F55: DPSG St. Rochus Rochusstraße 223 53123 Bonn Germany | G55: Germany | H55: Deutsche Pfadfinderschaft Sankt Georg | I55: DPSG St. Rochus | J55: Pfadfinder | K55: Bonn | L55: 9 | M55: 3 | N55: Friday | O55: 15:00 - 18:00 | P55: Monday | Q55: 12:00 - 15:00 | R55: Hello, we've got two boys in our troop that have diagnosis in the field of adhd and autism that we want to include in our group activities. To do this we need to increase the number of leaders. We are looking forward to this Intercamp! Cheers Annika | S55: IST-17682 | T55: 300 | U55: Mollie | V55: 2024-12-07 20:38:29 | W55: 1733603909 | Z55: 3
A56: 47 | B56: Wolfgang | C56: Otto | D56: scouterwolfgang@aol.com | E56: +4915753131324 | G56: Germany | H56: Deutsche Pfadfinderschaft Sankt Georg | I56: DPSG Moers St. Josef | J56: 14/08/01 | K56: Moers | L56: 1 | M56: 1 | N56: Friday | O56: 15:00 - 18:00 | P56: Monday | Q56: 09:00 - 12:00 | S56: IST-61800 | T56: 50 | U56: Mollie | V56: 2024-12-07 20:57:29 | W56: 1733605049 | Z56: 4
A57: 111 | B57: Wolfgang | C57: Otto | D57: scouterwolfgang@aol.com | E57: +4915753131324 | G57: Germany | H57: Deutsche Pfadfinderschaft Sankt Georg | I57: DPSG Moers St. Josef | J57: 14/08/01 | K57: Moers | L57: 17 | M57: 3 | N57: Friday | O57: 18:00 - 21:00 | P57: Monday | Q57: 09:00 - 12:00 | R57: Our Trailer is part of our kitchen. So it has to sty on our campsite! | S57: IST-21261 | T57: 500 | U57: Mollie | V57: 2025-02-17 01:00:14 | W57: 1739754014 | Z57: 4
A58: 21 | B58: Des | C58: Mahon | D58: des.mahon@arrowscouts.org.uk | E58: +447809149414 | F58: Des Mahon 3rd Chandlers Ford Scouts Arrow District | G58: GB | H58: British Guides In Foreign Countrys | I58: 3rd Chandler’s Ford | J58: 3rd | K58: Chandler’s Ford | L58: 6 | M58: 2 | N58: Friday | O58: 15:00 - 18:00 | P58: Monday | Q58: 09:00 - 12:00 | R58: Partnering with 1st Prague Scouts as we are sharing equipment | S58: IST-11133 | T58: 200 | U58: Mollie | V58: 2024-11-30 23:26:03 | W58: 1733009163 | Z58: 2
A59: 17 | B59: Christopher | C59: Wait | D59: waitchris0103@gmail.com | E59: +420777216228 | F59: 1st Prague (Czech Republic) Scout Group z.s. – British Scouting Overseas Pod pekárnami 251/4, Vysočany, 190 00 Praha 9 ICO: 04755057 | G59: GB | H59: BSO | I59: 1st Prague Scouts | J59: 04755057 | K59: Prague | L59: 29 | M59: 6 | N59: Friday | O59: 09:00 - 12:00 | P59: Monday | Q59: 12:00 - 15:00 | S59: IST-11133 | T59: 875 | U59: Mollie | V59: 2024-11-30 23:10:31 | W59: 1733008231 | Z59: 2
A60: 49 | B60: Zuzana | C60: Holekova | D60: zuzanaholekova@centrum.sk | E60: +421905886516 | G60: Slovakia | H60: Choose... | I60: Zbor Irmy Ševcechovej | J60: 31 | K60: Trenčianska Teplá | L60: 2 | M60: 1 | N60: Friday | O60: 15:00 - 18:00 | P60: Monday | Q60: 12:00 - 15:00 | S60: IST-35004 | T60: 75 | U60: Mollie | V60: 2024-12-08 13:07:16 | W60: 1733663236 | Z60: 2
A61: 16 | B61: Vladimir | C61: Bilek | D61: v.bilek@email.cz | E61: +352621277044 | F61: same as above | G61: Luxembourg | H61: Guests | I61: Telstar scouts international | J61: 12345 | K61: Luxembourg | L61: 30 | M61: 5 | N61: Friday | O61: 18:00 - 21:00 | P61: Monday | Q61: 09:00 - 12:00 | S61: IST-23477 | T61: 875 | U61: Mollie | V61: 2024-11-30 23:10:24 | W61: 1733008224 | Z61: 3
A62: 44 | B62: Zuzana | C62: Holekova | D62: zuzanaholekova@centrum.sk | E62: +421905886516 | G62: Slovakia | H62: Guests | I62: zbor Irmy Ševcechovej | J62: 31 | K62: Trenčianska Teplá | L62: 5 | M62: 1 | N62: Friday | O62: 15:00 - 18:00 | P62: Monday | Q62: 12:00 - 15:00 | S62: IST-10569 | T62: 150 | U62: Mollie | V62: 2024-12-07 19:33:48 | W62: 1733600028 | Z62: 2
A63: 139 | B63: András | C63: Imregh | G63: Hungary | H63: Magyar Cserkészszövetség | K63: Budapest | L63: 12 | M63: 5 | N63: Friday | O63: 15:00 - 18:00 | P63: Monday | Q63: 09:00 - 12:00 | X63: 575 euro to be paid | Y63: 575 | Z63: 3
A64: 18 | B64: Nigel | C64: Fleetwood | D64: agsl2-6thgosport@gosportscouts.org.uk | E64: +447812674516 | F64: 6th Gosport Air Scout Group | G64: GB | H64: BSO | I64: 6th Gosport Air Scout Group | J64: 6th | K64: Gosport | L64: 17 | M64: 5 | N64: Friday | O64: 12:00 - 15:00 | P64: Monday | Q64: 12:00 - 15:00 | S64: IST-11133 | T64: 550 | U64: Mollie | V64: 2024-11-30 23:11:03 | W64: 1733008263 | Z64: 1
A65: 84 | B65: Aleksandra | C65: Comblik | D65: aleksandra.comblik@zhp.net.pl | E65: +48510361821 | G65: Poland | H65: Zwiazek Harcerstwa Polskiego | I65: Silva | J65: 76 | K65: Gdansk | L65: 13 | M65: 1 | N65: Friday | O65: 12:00 - 15:00 | P65: Monday | Q65: 09:00 - 12:00 | S65: IST-12664 | T65: 350 | U65: Mollie | V65: 2025-02-04 14:27:42 | W65: 1738679262 | Z65: 3
A66: 86 | B66: Karolina | C66: Pazdro | D66: karolina.pazdro@zhp.net.pl | E66: +48609724261 | G66: Poland | H66: Zwiazek Harcerstwa Polskiego | I66: Brzęczące Chrabąszcze | J66: 16 | K66: Kraków | L66: 5 | M66: 1 | N66: Friday | O66: 15:00 - 18:00 | P66: Monday | Q66: 09:00 - 12:00 | S66: IST-12955 | T66: 150 | U66: Mollie | V66: 2025-02-05 12:07:35 | W66: 1738757255 | Z66: 4
A67: 87 | B67: Magdalena | C67: Szymczak | D67: szymczak.magdalena@zhp.net.pl | E67: +48786087728 | G67: Poland | H67: Zwiazek Harcerstwa Polskiego | I67: Łosie z Górnej półki | J67: 222 | K67: Łódź | L67: 13 | M67: 2 | N67: Friday | O67: 18:00 - 21:00 | P67: Monday | Q67: 09:00 - 12:00 | S67: IST-22412 | T67: 375 | U67: Mollie | V67: 2025-02-05 12:18:04 | W67: 1738757884 | Z67: 4
A68: 88 | B68: Natalia | C68: Gwizd | D68: natalia.gwizd@zhp.net.pl | E68: +48607781951 | G68: Poland | H68: Zwiazek Harcerstwa Polskiego | I68: Polish Eagles | J68: 882 | K68: Łódź | L68: 15 | M68: 2 | N68: Friday | O68: 18:00 - 21:00 | P68: Monday | Q68: 09:00 - 12:00 | S68: IST-10548 | T68: 425 | U68: Mollie | V68: 2025-02-05 12:21:04 | W68: 1738758064 | Z68: 4
A69: 89 | B69: Natasza | C69: Pytlarczyk | D69: natasza.pytlarczyk@zhp.net.pl | E69: +48792891243 | G69: Poland | H69: Zwiazek Harcerstwa Polskiego | I69: bunt | J69: 32 | K69: Warszawa Praga-Południe | L69: 8 | M69: 2 | N69: Friday | O69: 18:00 - 21:00 | P69: Monday | Q69: 09:00 - 12:00 | S69: IST-31219 | T69: 250 | U69: Mollie | V69: 2025-02-05 12:32:31 | W69: 1738758751 | Z69: 4
A70: 90 | B70: Joanna | C70: Poniatowska | D70: joanna.poniatowska@zhp.net.pl | E70: +48509069268 | G70: Poland | H70: Zwiazek Harcerstwa Polskiego | I70: 13 WDH - patrol harcerski | J70: 13 | K70: Złotokłos | L70: 15 | M70: 2 | N70: Friday | O70: 18:00 - 21:00 | P70: Monday | Q70: 09:00 - 12:00 | S70: IST-12701 | T70: 425 | U70: Mollie | V70: 2025-02-05 12:35:14 | W70: 1738758914 | Z70: 3
A71: 91 | B71: Oskar | C71: Kostyrka | D71: oskar.kostyrka@zhp.net.pl | E71: +48535003542 | G71: Poland | H71: Zwiazek Harcerstwa Polskiego | I71: 13WDH patrol starszoharcerski | J71: 13 | K71: Złotokłos | L71: 14 | M71: 2 | N71: Friday | O71: 15:00 - 18:00 | P71: Monday | Q71: 09:00 - 12:00 | S71: IST-17219 | T71: 400 | U71: Mollie | V71: 2025-02-05 12:37:30 | W71: 1738759050 | Z71: 3
A72: 92 | B72: Patryk | C72: Konieczny | D72: patryk.konieczny@zhp.net.pl | E72: +48501679756 | G72: Poland | H72: Zwiazek Harcerstwa Polskiego | I72: Czarne Siódemki | J72: 347 | K72: Cieszyn | L72: 12 | M72: 2 | N72: Friday | O72: 15:00 - 18:00 | P72: Monday | Q72: 09:00 - 12:00 | R72: We would like to be as close as possible on intercamp campsite to our friendly scout team called Watrzaki. Thanks in advance. | S72: IST-10906 | T72: 350 | U72: Mollie | V72: 2025-02-05 12:39:54 | W72: 1738759194 | Z72: 1
A73: 93 | B73: Nikola | C73: Mulewska | D73: nikola.mulewska@zhp.net.pl | E73: +48505834404 | G73: Poland | H73: Zwiazek Harcerstwa Polskiego | I73: 71N | J73: 71 | K73: Gdańsk | L73: 8 | M73: 1 | N73: Friday | O73: 15:00 - 18:00 | P73: Monday | Q73: 09:00 - 12:00 | R73: In there is an option we wolud like to be togeter with 71A, 76 Silva, 74 GDH „Kotwice”, 78 Dianthus and when still tehre is posibility we would like to be also with 98 Płomienne zorze, 94 GDSH ,,Venga, vamos!", Nebula. Thank you! | S73: IST-17468 | T73: 225 | U73: Mollie | V73: 2025-02-05 14:07:06 | W73: 1738764426 | Z73: 3
A74: 94 | B74: Adrianna | C74: Gutowska | D74: adrianna.gutowska@zhp.net.pl | E74: +48780121856 | G74: Poland | H74: Zwiazek Harcerstwa Polskiego | I74: 71 A | J74: 71 | K74: Gdańsk | L74: 7 | M74: 2 | N74: Friday | O74: 12:00 - 15:00 | P74: Monday | Q74: 09:00 - 12:00 | R74: We are together with 71 N so the amount of children is 15 and we have 3 leaders. So proportions are Preserved. | S74: IST-11512 | T74: 225 | U74: Mollie | V74: 2025-02-05 14:14:47 | W74: 1738764887 | Z74: 3
A75: 95 | B75: Zuzanna | C75: Stankiewicz | D75: zuzanna.stankiewicz1@zhp.net.pl | E75: +48535225116 | G75: Poland | H75: Zwiazek Harcerstwa Polskiego | I75: Płomienne Zorze | J75: 98 | K75: Gdańsk | L75: 7 | M75: 1 | N75: Friday | O75: 12:00 - 15:00 | P75: Monday | Q75: 09:00 - 12:00 | R75: In there is an option we wolud like to be togeter with 71A, 71N, 76 Silva, 74 GDH „Kotwice”, 78 Dianthus and when still tehre is posibility we would like to be also with, 94 GDSH ,,Venga, vamos!", Nebula. Thank you! | S75: IST-20772 | T75: 200 | U75: Mollie | V75: 2025-02-05 14:19:18 | W75: 1738765158 | Z75: 3
A76: 96 | B76: Michał | C76: Wnuk | D76: michal.wnuk@zhp.net.pl | E76: +48602672459 | G76: Poland | H76: Zwiazek Harcerstwa Polskiego | I76: Zawiercie 1 | J76: 1 | K76: Zawiercie | L76: 13 | M76: 2 | N76: Friday | O76: 15:00 - 18:00 | P76: Monday | Q76: 09:00 - 12:00 | R76: We ask that the camping area for the patrol "zawiercie 1" and "zawiercie 2" be next to each other. We are the same large group from one city. Would it be possible for us to spend the night on Thursday at the convention site? | S76: IST-63079 | T76: 375 | U76: Mollie | V76: 2025-02-05 14:21:53 | W76: 1738765313 | Z76: 2
A77: 97 | B77: Katarzyna | C77: Krzepkowska | D77: hufiec@zawiercie.zhp.pl | E77: +48602672459 | G77: Poland | H77: Zwiazek Harcerstwa Polskiego | I77: Zawiercie 2 | J77: 2 | K77: Zawiercie | L77: 13 | M77: 2 | N77: Friday | O77: 15:00 - 18:00 | P77: Monday | Q77: 09:00 - 12:00 | R77: We ask that the camping area for the patrol "zawiercie 1" and "zawiercie 2" be next to each other. We are the same large group from one city. Would it be possible for us to spend the night on Thursday at the convention site? | S77: IST-10147 | T77: 375 | U77: Mollie | V77: 2025-02-05 14:25:33 | W77: 1738765533 | Z77: 2
A78: 98 | B78: Jacek | C78: Słaby | D78: jacek.slaby@zhp.net.pl | E78: +48502039396 | G78: Poland | H78: Zwiazek Harcerstwa Polskiego | I78: 30 WDH | J78: 30 | K78: Warszawa | L78: 7 | M78: 1 | N78: Friday | O78: 15:00 - 18:00 | P78: Monday | Q78: 09:00 - 12:00 | S78: IST-19825 | T78: 200 | U78: Mollie | V78: 2025-02-05 14:30:41 | W78: 1738765842 | Z78: 2
A79: 99 | B79: Marta | C79: Zielińska | D79: marta.zielinska@zhp.net.pl | E79: +48535775774 | G79: Poland | H79: Zwiazek Harcerstwa Polskiego | I79: 424 DS "Żywioły" | J79: 424 | K79: Izabelin | L79: 13 | M79: 2 | N79: Friday | O79: 18:00 - 21:00 | P79: Monday | Q79: 09:00 - 12:00 | S79: IST-11217 | T79: 375 | U79: Mollie | V79: 2025-02-05 15:33:27 | W79: 1738769607 | Z79: 2
A80: 107 | B80: Karolina | C80: Litwińska | D80: karolina.liwinska@zhp.net.pl | E80: +48 799196515 | F80: Strumień 58 | G80: Poland | H80: Zwiazek Harcerstwa Polskiego | I80: Strumień 58 | J80: 58 | K80: Łódź | L80: 14 | M80: 2 | N80: Friday | O80: 18:00 - 21:00 | P80: Monday | Q80: 09:00 - 12:00 | S80: IST-17075 | T80: 375 | U80: Mollie | V80: 2025-02-16 21:27:46 | W80: 1739741266 | X80: Plus 1 to pay | Z80: 3
A81: 108 | B81: Michał | C81: Święcicki | D81: michal.swiecicki@zhp.net.pl | E81: +48511267708 | G81: Poland | H81: Zwiazek Harcerstwa Polskiego | I81: Granda | J81: 420 | K81: Warszawa | L81: 8 | M81: 2 | N81: Friday | O81: 18:00 - 21:00 | P81: Monday | Q81: 09:00 - 12:00 | S81: IST-20570 | T81: 250 | U81: Mollie | V81: 2025-02-16 21:37:27 | W81: 1739741847 | Z81: 2
A82: 109 | B82: Julia | C82: Kinderman | D82: julia.kinderman@zhp.net.pl | E82: +48519656858 | G82: Poland | H82: Zwiazek Harcerstwa Polskiego | I82: Gwardians | J82: 96 | K82: Łódź | L82: 14 | M82: 2 | N82: Friday | O82: 12:00 - 15:00 | P82: Monday | Q82: 09:00 - 12:00 | S82: IST-18637 | T82: 400 | U82: Mollie | V82: 2025-02-16 21:41:39 | W82: 1739742099 | Z82: 2
A83: 110 | B83: Damian | C83: Wojciechowski | D83: damian.wojciechowski@zhp.net.pl | E83: +48530259321 | G83: Poland | H83: Zwiazek Harcerstwa Polskiego | I83: 7 DH Arkana | J83: 7 | K83: Ząbki | L83: 15 | M83: 2 | N83: Friday | O83: 15:00 - 18:00 | P83: Monday | Q83: 09:00 - 12:00 | S83: IST-20119 | T83: 425 | U83: Mollie | V83: 2025-02-16 21:44:20 | W83: 1739742260 | Z83: 1
A84: 114 | B84: Emilia | C84: Skrzypek | D84: emilia.skrzypek@zhp.net.pl | E84: +48530259321 | G84: Poland | H84: Zwiazek Harcerstwa Polskiego | I84: Czata wymiata | J84: 19 | K84: Mosina | L84: 15 | M84: 2 | N84: Friday | O84: 15:00 - 18:00 | P84: Monday | Q84: 09:00 - 12:00 | S84: IST-96201 | T84: 425 | U84: Mollie | V84: 2025-02-23 18:30:20 | W84: 1740335420 | Z84: 1
A85: 115 | B85: Patrycja | C85: Kiryluk | D85: patrycja.kiryluk@zhp.net.pl | E85: +48 604948623 | G85: Poland | H85: Zwiazek Harcerstwa Polskiego | I85: FDDH 2 | J85: 2 | K85: Morąg | L85: 15 | M85: 2 | N85: Friday | O85: 09:00 - 12:00 | P85: Monday | Q85: 09:00 - 12:00 | R85: We would be grateful if you could place our two teams, FDDH 1 and FDDH 2, in the same subcamp during the Intercamp. We don’t have enough equipment to divide between the teams, and we are part of the same scout group. | S85: IST-83825 | T85: 400 | U85: Mollie | V85: 2025-02-23 18:34:30 | W85: 1740335670 | X85: Plus 1 to pay | Z85: 2
A86: 116 | B86: Kamil | C86: Sagan | D86: kamil.sagan@zhp.net.pl | E86: +48795599749 | G86: Poland | H86: Zwiazek Harcerstwa Polskiego | I86: HSDeserterzy | J86: 9 | K86: Kraków | L86: 10 | M86: 2 | N86: Friday | O86: 18:00 - 21:00 | P86: Monday | Q86: 09:00 - 12:00 | S86: IST-16632 | T86: 300 | U86: Mollie | V86: 2025-02-23 18:38:33 | W86: 1740335913 | Z86: 2
A87: 117 | B87: Jakub | C87: Jędras | D87: jakub.jedras@zhp.net.pl | E87: +48606891044 | G87: Poland | H87: Zwiazek Harcerstwa Polskiego | I87: HSDeserterki | J87: 9 | K87: Kraków | L87: 5 | M87: 1 | N87: Friday | O87: 15:00 - 18:00 | P87: Monday | Q87: 09:00 - 12:00 | S87: IST-17214 | T87: 150 | U87: Mollie | V87: 2025-02-23 18:44:55 | W87: 1740336295 | Z87: 2
A88: 118 | B88: Maciej | C88: Rogowicz | D88: maciej.rogowicz@zhp.net.pl | E88: +48666677498 | G88: Poland | H88: Zwiazek Harcerstwa Polskiego | I88: Nebula | J88: 141 | K88: Gdańsk | L88: 16 | M88: 1 | N88: Friday | O88: 15:00 - 18:00 | P88: Monday | Q88: 09:00 - 12:00 | R88: We wolud like to be togeter with 76 Silva, 74 Kotwice, 71A and 71N, plomienne zorze, venda vamos and diathus, if it is possible or at least partly together | S88: IST-19439 | T88: 425 | U88: Mollie | V88: 2025-02-23 18:49:46 | W88: 1740336586 | Z88: 3
A89: 119 | B89: Dominik Jeffrey | C89: Rimaszauskas | D89: dominik.rimaszauskas@zhp.net.pl | E89: +48535037130 | G89: Poland | H89: Zwiazek Harcerstwa Polskiego | I89: FDDH 1 | J89: 8 | K89: MORĄG | L89: 15 | M89: 2 | N89: Friday | O89: 15:00 - 18:00 | P89: Monday | Q89: 09:00 - 12:00 | S89: IST-33514 | T89: 425 | U89: Mollie | V89: 2025-02-23 18:53:04 | W89: 1740336784 | Z89: 2
A90: 120 | B90: Izabela | C90: Kucmin-Bemelmans | D90: izabela.kucmin-bemelmans@zhp.net.pl | E90: +48692277074 | G90: Poland | H90: Zwiazek Harcerstwa Polskiego | I90: Skalne Nietoperze | J90: 89 | K90: Biały Kościół | L90: 15 | M90: 2 | N90: Friday | O90: 15:00 - 18:00 | P90: Monday | Q90: 09:00 - 12:00 | S90: IST-18955 | T90: 425 | U90: Mollie | V90: 2025-02-23 19:26:55 | W90: 1740338815 | Z90: 1
A91: 121 | B91: Sabina | C91: Konieczny | D91: sabina.konieczny@zhp.net.pl | E91: +48 | G91: Poland | H91: Zwiazek Harcerstwa Polskiego | I91: Watrzaki | J91: 25 | K91: Brenna | L91: 11 | M91: 1 | N91: Friday | O91: 18:00 - 21:00 | P91: Monday | Q91: 09:00 - 12:00 | R91: We come to intercamp with "Czarne Siódemki" team and we ask you to be together at the camp. | S91: IST-18013 | T91: 300 | U91: Mollie | V91: 2025-02-23 19:35:56 | W91: 1740339356 | Z91: 1
A92: 122 | B92: Julia | C92: Sało | D92: julia.salo@zhp.net.pl | E92: +48513504409 | G92: Poland | H92: Zwiazek Harcerstwa Polskiego | I92: Feniksiątka | J92: 234 | K92: Warszawa | L92: 9 | M92: 2 | N92: Friday | O92: 15:00 - 18:00 | P92: Monday | Q92: 09:00 - 12:00 | R92: Our patrol is from one team with the Feniksiaki patrol (leader-Joanna Zubek). If it would be possible, we would appreciate being located at a common camping spot, as we will share tents and equipment. Likewise with activities-we will be grateful if our hikes and activities are scheduled on the same days. | S92: IST-17697 | T92: 275 | U92: Mollie | V92: 2025-02-23 20:21:28 | W92: 1740342088 | Z92: 3
A93: 123 | B93: Dorota | C93: Kułaga | D93: dorota.kulaga@zhp.net.pl | E93: +48510454231 | G93: Poland | H93: Zwiazek Harcerstwa Polskiego | I93: 74 GDH „Kotwice” | J93: 74 | K93: Gdańsk | L93: 8 | M93: 2 | N93: Friday | O93: 15:00 - 18:00 | P93: Monday | Q93: 09:00 - 12:00 | R93: If possible we would like to be togetger with all troops from Gdańsk or partly with them. (71A, 71N, 76 Silva, 141 Nebula, plomienne zorze, venda vamos, diathus) | S93: IST-31679 | T93: 250 | U93: Mollie | V93: 2025-02-23 20:30:09 | W93: 1740342609 | Z93: 3
A94: 124 | B94: Aleksandra | C94: Mocarska | D94: aleksandra.mocarska@zhp.net.pl | E94: +48881202503 | G94: Poland | H94: Zwiazek Harcerstwa Polskiego | I94: Dianthus | J94: 78 | K94: Gdańsk | L94: 8 | M94: 1 | N94: Friday | O94: 15:00 - 18:00 | P94: Monday | Q94: 09:00 - 12:00 | R94: If possible we would like to be together with 71A, 71N, 76 Silva, 74 Kotwice, 141 Nebula, plomienne zorze and venda vamos. Thank you! | S94: IST-10409 | T94: 225 | U94: Mollie | V94: 2025-02-23 20:34:23 | W94: 1740342863 | Z94: 3
A95: 133 | B95: Joanna | C95: Zubek | D95: joanna.zubek@zhp.net.pl | E95: +48 534152804 | G95: Poland | H95: Zwiazek Harcerstwa Polskiego | I95: Feniksiaki | J95: 234 | K95: Warszawa | L95: 10 | M95: 2 | N95: Friday | O95: 15:00 - 18:00 | P95: Monday | Q95: 09:00 - 12:00 | R95: Our patrol is from one team with the Feniksiątka patrol (leader-Julia Sało). If it would be possible, we would appreciate being located at a common camping spot, as we will share tents and equipment. Likewise with activities-we will be grateful if our hikes and activities are scheduled on the same days. | S95: IST | X95: 300 euro to be paid | Y95: 300 | Z95: 3
A96: 134 | B96: Pola | C96: Drygiel | D96: pola.drygiel@zhp.pl | E96: +48 602497212 | G96: Poland | H96: Zwiazek Harcerstwa Polskiego | I96: Kociaki górą | J96: 211 | K96: warszawa | L96: 9 | M96: 2 | N96: Friday | O96: 15:00 - 18:00 | P96: Monday | Q96: 09:00 - 12:00 | X96: 275 euro to be paid | Y96: 275 | Z96: 4
A97: 135 | B97: Sabina | C97: Gurowiec | D97: sabina.gurowiec@zhp.net.pl | E97: +48 509632613 | G97: Poland | H97: Zwiazek Harcerstwa Polskiego | I97: 16 Drużyna Harcerska Tarnowskie Góry | J97: 16 | K97: Tarnowskie Góry | L97: 15 | M97: 2 | N97: Friday | O97: 15:00 - 18:00 | P97: Monday | Q97: 09:00 - 12:00 | X97: 425 euro to be paid | Y97: 425 | Z97: 4
A98: 136 | B98: Katarzyna | C98: Kwiatkowska | D98: katarzyna.kwiatkowska@zhp.net.pl | E98: +48 502601077 | G98: Poland | H98: Zwiazek Harcerstwa Polskiego | I98: Włóczykije 1 | J98: 30 WDH | K98: Warszawa | L98: 7 | M98: 2 | N98: Friday | O98: 15:00 - 18:00 | P98: Monday | Q98: 09:00 - 12:00 | X98: 225 euro to be paid | Y98: 225 | Z98: 2
A99: 137 | B99: Stanisław | C99: Szymczykowski | D99: stanislaw.szymczykowski@zhp.net.pl | E99: +48 784118055 | G99: Poland | H99: Zwiazek Harcerstwa Polskiego | I99: Błękitny Zenit | J99: 147 | K99: Warszawa | L99: 7 | M99: 2 | N99: Friday | O99: 15:00 - 18:00 | P99: Monday | Q99: 09:00 - 12:00 | X99: 225 euro to be paid | Y99: 225 | Z99: 3
A100: 138 | B100: Iga | C100: Woźniak | D100: iga.wozniak@zhp.net.pl | E100: +48 516061590 | G100: Poland | H100: Zwiazek Harcerstwa Polskiego | I100: 94 GDSH ,,Venga, vamos!" | J100: 94 | K100: Gdańsk | L100: 7 | M100: 1 | N100: Friday | O100: 15:00 - 18:00 | P100: Monday | Q100: 09:00 - 12:00 | X100: 200 euro to be paid | Y100: 200 | Z100: 3
...

Sheet Subcamp 1
A1: No | B1: First name | C1: Last name | D1: Email | E1: Mobile phone | F1: Invoice details | G1: Country | H1: Scout Association | I1: Troop name | J1: Troop organisation number | K1: City | L1: Number of Children | M1: Number of Leaders | N1: Arrival day | O1: Arrival time | P1: Departure day | Q1: Departure time | R1: Further remarks (optional) | S1: Order Number | T1: Total Costs | U1: Payment Type | V1: Registration time | W1: Order Number2 | X1: Additional registrants | Y1: Comments RJ: | Z1: Subcamp
A2: {=_xlfn._xlws.FILTER('All Subcamps'!A2:Z139,'All Subcamps'!Z2:Z139=1)} -> 59 | B2: Barbora | C2: Jánská | D2: janskabarbora@gmail.com | E2: +420733650318 | F2: 0 | G2: Czech Republic | H2: JUNAK - cesky skaut | I2: Dráčata Štěnovice | J2: 323.02 | K2: Štěnovice | L2: 20 | M2: 4 | N2: Friday | O2: 18:00 - 21:00 | P2: Monday | Q2: 09:00 - 12:00 | R2: 0 | S2: IST-69112 | T2: 600 | U2: Mollie | V2: 2025-01-13 14:28:34 | W2: 1736778514 | X2: 0 | Y2: 0 | Z2: 1
A3: 65 | B3: Jan | C3: Holoubek | D3: jan.holoubek@skaut.cz | E3: +420736149229 | F3: 0 | G3: Czech Republic | H3: JUNAK - cesky skaut | I3: Stopa | J3: 526.06.004 | K3: Hradec Králové | L3: 6 | M3: 2 | N3: Friday | O3: 12:00 - 15:00 | P3: Monday | Q3: 09:00 - 12:00 | R3: We need to be two adults for safety reasons (two drivers). Also we both work with the troop during the year as mentors. | S3: IST-54674 | T3: 200 | U3: Mollie | V3: 2025-01-22 16:15:01 | W3: 1737562501 | X3: 0 | Y3: 0 | Z3: 1
A4: 66 | B4: Vojtěch | C4: Podzimek | D4: podzimek.vojta@skaut.cz | E4: +420724144345 | F4: Junák - český skaut, středisko Sopka Nová Paka, z. s. Svatojánská 1193 509 01 Nová Paka IČ: 60116421 | G4: Czech Republic | H4: JUNAK - cesky skaut | I4: Sopka Nová Paka | J4: 522.03 | K4: NOVÁ PAKA | L4: 20 | M4: 4 | N4: Friday | O4: 18:00 - 21:00 | P4: Monday | Q4: 09:00 - 12:00 | R4: 0 | S4: IST-16688 | T4: 600 | U4: Mollie | V4: 2025-01-22 20:56:18 | W4: 1737579378 | X4: 0 | Y4: 0 | Z4: 1
A5: 100 | B5: Filip | C5: Fišer | D5: fiser-filip@seznam.cz | E5: +420731993016 | F5: Junák - český skaut, středisko Vamberk, z. s. Ič.: 42885311 V Lukách 598, 517 54 Vamberk | G5: Czech Republic | H5: JUNAK - cesky skaut | I5: 2. Oddíl (DSS) | J5: 524.09.002 | K5: Vamberk | L5: 6 | M5: 2 | N5: Friday | O5: 09:00 - 12:00 | P5: Monday | Q5: 09:00 - 12:00 | R5: the second leader Jaroslav Vašátko +420 733 580 760 jaroslav.vasatko@seznam.cz | S5: IST-21179 | T5: 200 | U5: Mollie | V5: 2025-02-07 14:42:26 | W5: 1738939346 | X5: 0 | Y5: 0 | Z5: 1
A6: 57 | B6: Ulrich | C6: Maurach | D6: mail@ulrich-maurach.de | E6: +491713141429 | F6: Team! I’m a german father (born in HH) of a 14 year old daughter and made my promise as a British Scout in Celle, Lower Saxony (Niedersachsen) during the 80’s. A became a Venture Scout during that time and attended only one Intercamp – must have been near the river Rhine close to Bernkastel-Kues. This year I would like to attend the Intercamp, to show my daughter, what a wonderful movement scouting is. I do offer being a ‘helper’ during the event where ever it is needed. So – is it possible to attend with 1 tent and two persons? I hope to hear from you - Ulrich Ulrich Maurach M +49171 3141429 mail@ulrich-maurach.de | G6: GB | H6: BSO | I6: Ulrich Maurach | J6: -/- | K6: Berlin | L6: 1 | M6: 1 | N6: Friday | O6: 15:00 - 18:00 | P6: Monday | Q6: 12:00 - 15:00 | R6: Team! I’m a german father (born in HH) of a 14 year old daughter and made my promise as a British Scout in Celle, Lower Saxony (Niedersachsen) during the 80’s. A became a Venture Scout during that time and attended only one Intercamp – must have been near the river Rhine close to Bernkastel-Kues. This year I would like to attend the Intercamp, to show my daughter, what a wonderful movement scouting is. I do offer being a ‘helper’ during the event where ever it is needed. So – is it possible to attend with 1 tent and two persons? I hope to hear from you - Ulrich Ulrich Maurach M +49171 3141429 mail@ulrich-maurach.de | S6: IST-45306 | T6: 50 | U6: Mollie | V6: 2025-01-09 08:35:01 | W6: 1736411701 | X6: 0 | Y6: 0 | Z6: 1
A7: 22 | B7: Robin | C7: Bandini | D7: vorstand@pfadfinder-bammental.de | E7: +491627911091 | F7: 0 | G7: Germany | H7: Deutsche Pfadfinderschaft Sankt Georg | I7: Stamm Karl Leisner | J7: 3363 | K7: Bammental | L7: 14 | M7: 3 | N7: Friday | O7: 18:00 - 21:00 | P7: Monday | Q7: 12:00 - 15:00 | R7: 0 | S7: IST-11133 | T7: 425 | U7: Mollie | V7: 2024-11-30 23:33:26 | W7: 1733009606 | X7: 0 | Y7: 0 | Z7: 1
A8: 24 | B8: Martin | C8: Babst | D8: martin.babst@web.de | E8: +4915126957577 | F8: 0 | G8: Germany | H8: Deutsche Pfadfinderschaft Sankt Georg | I8: Maximilan Kolbe Lammersdorf | J8: 010607 | K8: Aachen | L8: 48 | M8: 9 | N8: Friday | O8: 12:00 - 15:00 | P8: Monday | Q8: 12:00 - 15:00 | R8: 0 | S8: IST-11133 | T8: 1425 | U8: Mollie | V8: 2024-12-01 00:20:50 | W8: 1733012451 | X8: 0 | Y8: 0 | Z8: 1
A9: 18 | B9: Nigel | C9: Fleetwood | D9: agsl2-6thgosport@gosportscouts.org.uk | E9: +447812674516 | F9: 6th Gosport Air Scout Group | G9: GB | H9: BSO | I9: 6th Gosport Air Scout Group | J9: 6th | K9: Gosport | L9: 17 | M9: 5 | N9: Friday | O9: 12:00 - 15:00 | P9: Monday | Q9: 12:00 - 15:00 | R9: 0 | S9: IST-11133 | T9: 550 | U9: Mollie | V9: 2024-11-30 23:11:03 | W9: 1733008263 | X9: 0 | Y9: 0 | Z9: 1
A10: 92 | B10: Patryk | C10: Konieczny | D10: patryk.konieczny@zhp.net.pl | E10: +48501679756 | F10: 0 | G10: Poland | H10: Zwiazek Harcerstwa Polskiego | I10: Czarne Siódemki | J10: 347 | K10: Cieszyn | L10: 12 | M10: 2 | N10: Friday | O10: 15:00 - 18:00 | P10: Monday | Q10: 09:00 - 12:00 | R10: We would like to be as close as possible on intercamp campsite to our friendly scout team called Watrzaki. Thanks in advance. | S10: IST-10906 | T10: 350 | U10: Mollie | V10: 2025-02-05 12:39:54 | W10: 1738759194 | X10: 0 | Y10: 0 | Z10: 1
A11: 110 | B11: Damian | C11: Wojciechowski | D11: damian.wojciechowski@zhp.net.pl | E11: +48530259321 | F11: 0 | G11: Poland | H11: Zwiazek Harcerstwa Polskiego | I11: 7 DH Arkana | J11: 7 | K11: Ząbki | L11: 15 | M11: 2 | N11: Friday | O11: 15:00 - 18:00 | P11: Monday | Q11: 09:00 - 12:00 | R11: 0 | S11: IST-20119 | T11: 425 | U11: Mollie | V11: 2025-02-16 21:44:20 | W11: 1739742260 | X11: 0 | Y11: 0 | Z11: 1
A12: 114 | B12: Emilia | C12: Skrzypek | D12: emilia.skrzypek@zhp.net.pl | E12: +48530259321 | F12: 0 | G12: Poland | H12: Zwiazek Harcerstwa Polskiego | I12: Czata wymiata | J12: 19 | K12: Mosina | L12: 15 | M12: 2 | N12: Friday | O12: 15:00 - 18:00 | P12: Monday | Q12: 09:00 - 12:00 | R12: 0 | S12: IST-96201 | T12: 425 | U12: Mollie | V12: 2025-02-23 18:30:20 | W12: 1740335420 | X12: 0 | Y12: 0 | Z12: 1
A13: 120 | B13: Izabela | C13: Kucmin-Bemelmans | D13: izabela.kucmin-bemelmans@zhp.net.pl | E13: +48692277074 | F13: 0 | G13: Poland | H13: Zwiazek Harcerstwa Polskiego | I13: Skalne Nietoperze | J13: 89 | K13: Biały Kościół | L13: 15 | M13: 2 | N13: Friday | O13: 15:00 - 18:00 | P13: Monday | Q13: 09:00 - 12:00 | R13: 0 | S13: IST-18955 | T13: 425 | U13: Mollie | V13: 2025-02-23 19:26:55 | W13: 1740338815 | X13: 0 | Y13: 0 | Z13: 1
A14: 121 | B14: Sabina | C14: Konieczny | D14: sabina.konieczny@zhp.net.pl | E14: +48 | F14: 0 | G14: Poland | H14: Zwiazek Harcerstwa Polskiego | I14: Watrzaki | J14: 25 | K14: Brenna | L14: 11 | M14: 1 | N14: Friday | O14: 18:00 - 21:00 | P14: Monday | Q14: 09:00 - 12:00 | R14: We come to intercamp with "Czarne Siódemki" team and we ask you to be together at the camp. | S14: IST-18013 | T14: 300 | U14: Mollie | V14: 2025-02-23 19:35:56 | W14: 1740339356 | X14: 0 | Y14: 0 | Z14: 1
A15: 13 | B15: Jorn | C15: Weijs | D15: jorn.weijs1997@live.nl | E15: +31620385792 | F15: 0 | G15: The Netherlands | H15: Scouting Nederland | I15: De Peelspeurders | J15: 1475 | K15: Venray | L15: 40 | M15: 8 | N15: Friday | O15: 12:00 - 15:00 | P15: Monday | Q15: 12:00 - 15:00 | R15: 0 | S15: IST-27230 | T15: 1200 | U15: Mollie | V15: 2024-11-30 20:01:30 | W15: 1732996890 | X15: 0 | Y15: 0 | Z15: 1
A16: 54 | B16: Marinus | C16: Hovius | D16: marinusfj@gmail.com | E16: +31641222084 | F16: 0 | G16: The Netherlands | H16: Scouting Nederland | I16: Scouting Den Oever | J16: 1234 | K16: Den Oever | L16: 25 | M16: 5 | N16: Friday | O16: 12:00 - 15:00 | P16: Monday | Q16: 12:00 - 15:00 | R16: 0 | S16: IST-13297 | T16: 750 | U16: Mollie | V16: 2024-12-20 13:03:49 | W16: 1734699829 | X16: 0 | Y16: 0 | Z16: 1
A17: 113 | B17: Rick | C17: Galeano | D17: rick_galeano@hotmail.com | E17: +491745407463 | F17: 0 | G17: United States | H17: Boy Scouts of America - Transatlantic Council | I17: Panzer Troop 44 | J17: 44 | K17: Boeblingen | L17: 10 | M17: 6 | N17: Friday | O17: 18:00 - 21:00 | P17: Monday | Q17: 09:00 - 12:00 | R17: 0 | S17: IST-17058 | T17: 400 | U17: Mollie | V17: 2025-02-23 17:37:11 | W17: 1740332231 | X17: 0 | Y17: 0 | Z17: 1
A18: 125 | B18: Roberto | C18: Baltazar | D18: bltzrr@gmail.com | E18: +494915117534988 | F18: 0 | G18: United States | H18: Boy Scouts of America - Transatlantic Council | I18: Radioactive | J18: 156 | K18: Ramstein | L18: 7 | M18: 3 | N18: Friday | O18: 18:00 - 21:00 | P18: Monday | Q18: 09:00 - 12:00 | R18: 0 | S18: IST-12623 | T18: 250 | U18: Mollie | V18: 2025-02-25 20:47:16 | W18: 1740516436 | X18: 0 | Y18: 0 | Z18: 1
A19: 132 | B19: Henry | C19: Williams | D19: tomnkt98@gmail.com | E19: +14104249248 | F19: 0 | G19: United States | H19: Boy Scouts of America - Transatlantic Council | I19: Scout Troop 154 (Boys) | J19: Troop 0154 (BT) | K19: Stuttgart | L19: 12 | M19: 3 | N19: Friday | O19: 12:00 - 15:00 | P19: Monday | Q19: 09:00 - 12:00 | R19: We also have a scout who paid with Troop 324, also from Stuttgart, but transferred to our troop. Please add that individual to our count so we are provided the correct number of camping slots, wristbands, patches, etc. Using three adults to assist with transportation of scouts and gear. Most of our scouts are on the the younger side, so the extra leader will help. | S19: IST-17804 | T19: 350 | U19: Mollie | V19: 2025-03-22 16:45:29 | W19: 1742661930 | X19: 0 | Y19: 0 | Z19: 1
L31: =SUM(L2:L20) -> 294 | M31: =SUM(M2:M20) -> 64 | N31: =L31+M31 -> 358

Sheet Subcamp 2
A1: No | B1: First name | C1: Last name | D1: Email | E1: Mobile phone | F1: Invoice details | G1: Country | H1: Scout Association | I1: Troop name | J1: Troop organisation number | K1: City | L1: Number of Children | M1: Number of Leaders | N1: Arrival day | O1: Arrival time | P1: Departure day | Q1: Departure time | R1: Further remarks (optional) | S1: Order Number | T1: Total Costs | U1: Payment Type | V1: Registration time | W1: Order Number2 | X1: Additional registrants | Y1: Comments RJ: | Z1: Subcamp
A2: {=_xlfn._xlws.FILTER('All Subcamps'!A2:Z139,'All Subcamps'!Z2:Z139=2)} -> 33 | B2: Joseph | C2: Monk | D2: joe.monk@britishscoutingoverseas.org.uk | E2: +32484266960 | F2: 0 | G2: Belgium | H2: FOS Open Scouting | I2: Central Brussels Scouts | J2: 112e | K2: Brussels | L2: 15 | M2: 5 | N2: Friday | O2: 21:00 - 00:00 | P2: Monday | Q2: 15:00 - 18:00 | R2: Arrival and Departure times are estimates. 2 additional Scouters needed due to logistical requirements to transport youth and equipment. | S2: IST-18979 | T2: 500 | U2: Mollie | V2: 2024-12-02 09:42:04 | W2: 1733132524 | X2: 0 | Y2: 0 | Z2: 2
A3: 30 | B3: Jonathan | C3: Copner | D3: jon.copner@britishscoutingoverseas.org.uk | E3: +32 | F3: Grootveldlaan 12, 3080 Tervuren, Belgium | G3: Belgium | H3: FOS Open Scouting | I3: Brussels Explorers | J3: FOS111 | K3: Tervuren | L3: 12 | M3: 3 | N3: Friday | O3: 18:00 - 21:00 | P3: Monday | Q3: 12:00 - 15:00 | R3: 3 leaders - 3 vehicles required | S3: IST-95976 | T3: 375 | U3: Mollie | V3: 2024-12-01 12:56:03 | W3: 1733057763 | X3: 0 | Y3: 0 | Z3: 2
A4: 62 | B4: Lenka | C4: Hechtová | D4: lenkalischkova@gmail.com | E4: +420607881402 | F4: 0 | G4: Czech Republic | H4: JUNAK - cesky skaut | I4: Core | J4: 511.02.004 | K4: Nový Bor | L4: 20 | M4: 4 | N4: Friday | O4: 18:00 - 21:00 | P4: Monday | Q4: 09:00 - 12:00 | R4: 0 | S4: IST-18688 | T4: 600 | U4: Mollie | V4: 2025-01-19 18:16:07 | W4: 1737310567 | X4: 0 | Y4: 0 | Z4: 2
A5: 63 | B5: Petr | C5: Kvarda | D5: kvardic.p@seznam.cz | E5: +420739528720 | F5: 0 | G5: Czech Republic | H5: JUNAK - cesky skaut | I5: Goliath | J5: 611.05 | K5: Přibyslav | L5: 8 | M5: 2 | N5: Friday | O5: 12:00 - 15:00 | P5: Monday | Q5: 15:00 - 18:00 | R5: 0 | S5: IST-12285 | T5: 250 | U5: Mollie | V5: 2025-01-20 17:26:18 | W5: 1737393978 | X5: 0 | Y5: 0 | Z5: 2
A6: 64 | B6: Klára | C6: Helánová | D6: akela.sebetov@skaut.cz | E6: +420777865883 | F6: Junák - Český skaut, středisko Severka, z.s. Šebetov 49 679 35 Czech Republic | G6: Czech Republic | H6: JUNAK - cesky skaut | I6: Středisko Severka | J6: 621.11 | K6: Šebetov | L6: 15 | M6: 3 | N6: Friday | O6: 15:00 - 18:00 | P6: Monday | Q6: 12:00 - 15:00 | R6: We are not sure about the arrival time yet. We're in the process of deciding between Friday morning (around 10 am) and evening (around 6 pm). We'll let you know once we've settled. | S6: IST-64335 | T6: 450 | U6: Mollie | V6: 2025-01-21 17:35:18 | W6: 1737480918 | X6: 0 | Y6: 0 | Z6: 2
A7: 77 | B7: Ondřej | C7: Rejsek | D7: ondrej.rejsek@seznam.cz | E7: +420605211206 | F7: Junák - český skaut, středisko Želivák Hradec Králové, z. s. Čajkovského 1861/46A, 500 09 Hradec Králové IČO: 62693158 | G7: Czech Republic | H7: JUNAK - cesky skaut | I7: Želivák | J7: 526.07 | K7: Hradec Králové | L7: 12 | M7: 3 | N7: Friday | O7: 09:00 - 12:00 | P7: Monday | Q7: 09:00 - 12:00 | R7: We have exceeded the participant rate, because two of the leaders are still rangers in the age of 18, which want to go together. We would like to give them the opportunity to gain experience in leadership - to participate in organization of the international event. In our opinion they should have the support of older and experienced leader. Unfortunately the number of scout - participants is a little bit lower than expected. | S7: IST-64944 | T7: 375 | U7: Mollie | V7: 2025-01-31 20:55:09 | W7: 1738356909 | X7: 0 | Y7: 0 | Z7: 2
A8: 78 | B8: Antonín | C8: Kala | D8: tonda.kala@seznam.cz | E8: +420603472473 | F8: 0 | G8: Czech Republic | H8: JUNAK - cesky skaut | I8: Stopaři | J8: 118.52 | K8: Praha | L8: 14 | M8: 2 | N8: Friday | O8: 15:00 - 18:00 | P8: Monday | Q8: 12:00 - 15:00 | R8: 0 | S8: IST-19283 | T8: 400 | U8: Mollie | V8: 2025-01-31 22:47:55 | W8: 1738363675 | X8: 0 | Y8: 0 | Z8: 2
A9: 80 | B9: Jiří | C9: Granát | D9: namornik@skaut.cz | E9: +420732310218 | F9: 0 | G9: Czech Republic | H9: JUNAK - cesky skaut | I9: Junák Kostelec nad Orlicí | J9: 524.03 | K9: Kostelec nad Orlicí | L9: 20 | M9: 4 | N9: Friday | O9: 09:00 - 12:00 | P9: Monday | Q9: 09:00 - 12:00 | R9: 0 | S9: IST-23514 | T9: 600 | U9: Mollie | V9: 2025-02-01 21:53:16 | W9: 1738446796 | X9: 0 | Y9: 0 | Z9: 2
A10: 103 | B10: Bára | C10: Matoušová | D10: matousova.bara@skaut.cz | E10: +420605989853 | F10: 0 | G10: Czech Republic | H10: JUNAK - cesky skaut | I10: Fata Morgana | J10: 523.1 | K10: Nové Město nad Metují | L10: 5 | M10: 1 | N10: Friday | O10: 09:00 - 12:00 | P10: Monday | Q10: 12:00 - 15:00 | R10: 0 | S10: IST-64369 | T10: 150 | U10: Mollie | V10: 2025-02-10 13:55:50 | W10: 1739195751 | X10: 0 | Y10: 0 | Z10: 2
A11: 104 | B11: Pavel | C11: Čechura | D11: pavelcechura@seznam.cz | E11: +420607927028 | F11: 0 | G11: Czech Republic | H11: JUNAK - cesky skaut | I11: Třebechovice | J11: 521.01 | K11: Třebechovice pod Orebem | L11: 20 | M11: 4 | N11: Friday | O11: 09:00 - 12:00 | P11: Monday | Q11: 09:00 - 12:00 | R11: 0 | S11: IST-84861 | T11: 600 | U11: Mollie | V11: 2025-02-10 16:39:41 | W11: 1739205581 | X11: 0 | Y11: 0 | Z11: 2
A12: 112 | B12: Michal | C12: Sýkora | D12: sykoramichal@skaut.cz | E12: +420739102827 | F12: 0 | G12: Czech Republic | H12: JUNAK - cesky skaut | I12: AD FONTES | J12: 621.08 | K12: Šebrov - Kateřina | L12: 20 | M12: 4 | N12: Friday | O12: 09:00 - 12:00 | P12: Monday | Q12: 09:00 - 12:00 | R12: 0 | S12: IST-54943 | T12: 600 | U12: Mollie | V12: 2025-02-17 21:05:42 | W12: 1739826342 | X12: 0 | Y12: 0 | Z12: 2
A13: 42 | B13: Lynn | C13: Millard | D13: lynn.millard@britishscoutingoverseas.org.uk | E13: +33637844303 | F13: 0 | G13: GB | H13: BSO | I13: 1st Maisons-Laffitte International | J13: lynn burns nutrition | K13: Maisons-Laffitte | L13: 10 | M13: 3 | N13: Friday | O13: 21:00 - 00:00 | P13: Monday | Q13: 12:00 - 15:00 | R13: Partnering with 1st Prague Scouts as we are sharing equipment - Added extra leader but if not needed will let you know. We have potential requirement for additional adult for neurodivergent kids/support driving. Rather book one extra and cancel than the other way around. | S13: IST-11256 | T13: 325 | U13: Mollie | V13: 2024-12-04 19:36:32 | W13: 1733340992 | X13: 0 | Y13: 0 | Z13: 2
A14: 20 | B14: Jonas | C14: Spinczyk | D14: Jonas.spinczyk@rdp-bund.de | E14: +491621979714 | F14: 0 | G14: Germany | H14: Deutsche Pfadfinderschaft Sankt Georg | I14: DPSG Kempen | J14: 01/02/12 | K14: Kempen | L14: 21 | M14: 5 | N14: Friday | O14: 15:00 - 18:00 | P14: Monday | Q14: 09:00 - 12:00 | R14: We need one more scout leader, because of a disabled participant. | S14: IST-11133 | T14: 650 | U14: Mollie | V14: 2024-11-30 23:17:00 | W14: 1733008620 | X14: 0 | Y14: 0 | Z14: 2
A15: 23 | B15: Sebastian | C15: Kiwitt | D15: s-kiwitt@outlook.de | E15: +4917622228294 | F15: Sebastian Kiwitt DPSG Stamm St. Viktor Xanten Schwarzer Weg 10 46509 Xanten | G15: Germany | H15: Deutsche Pfadfinderschaft Sankt Georg | I15: DPSG Stamm St. Viktor Xanten | J15: 140101 | K15: Xanten | L15: 27 | M15: 7 | N15: Friday | O15: 12:00 - 15:00 | P15: Monday | Q15: 12:00 - 15:00 | R15: We need more Leeders, because we come with two Leeder by Car and the others with the Kids by Train. And I think Four Leeders with 27 Kids is not so safety. I hope this is Ok for you. Thank you. Best regards Sebastian | S15: IST-11133 | T15: 850 | U15: Mollie | V15: 2024-11-30 23:36:13 | W15: 1733009773 | X15: 0 | Y15: 0 | Z15: 2
A16: 35 | B16: Lale | C16: Akman | D16: laleakman@yahoo.de | E16: +4917684098636 | F16: Eichendorffstraße 8, 68167 Mannheim | G16: Germany | H16: Deutsche Pfadfinderschaft Sankt Georg | I16: St. Bernhard | J16: 070101 | K16: Mannheim | L16: 15 | M16: 4 | N16: Friday | O16: 12:00 - 15:00 | P16: Monday | Q16: 15:00 - 18:00 | R16: 0 | S16: IST-17058 | T16: 475 | U16: Mollie | V16: 2024-12-02 18:01:18 | W16: 1733162478 | X16: 0 | Y16: 0 | Z16: 2
A17: 36 | B17: Fabian | C17: Berger | D17: bigberger@gmx.de | E17: +4917620771317 | F17: 0 | G17: Germany | H17: Deutsche Pfadfinderschaft Sankt Georg | I17: DPSG Stamm Cherusker | J17: 0007010300 | K17: Laudenbach | L17: 13 | M17: 2 | N17: Friday | O17: 15:00 - 18:00 | P17: Monday | Q17: 12:00 - 15:00 | R17: 0 | S17: IST-18820 | T17: 375 | U17: Mollie | V17: 2024-12-02 18:30:47 | W17: 1733164247 | X17: 0 | Y17: 0 | Z17: 2
A18: 37 | B18: Malte | C18: Grönemann | D18: malte.groenemann@dpsg-friedrichsfeld.de | E18: +4917641629411 | F18: 0 | G18: Germany | H18: Deutsche Pfadfinderschaft Sankt Georg | I18: DPSG St. Bonifatius Mannheim | J18: 070106 | K18: Mannheim | L18: 9 | M18: 2 | N18: Friday | O18: 18:00 - 21:00 | P18: Monday | Q18: 12:00 - 15:00 | R18: 0 | S18: IST-96584 | T18: 200 | U18: Mollie | V18: 2024-12-02 18:49:22 | W18: 1733165362 | X18: 0 | Y18: add. 3 kids | Z18: 2
A19: 38 | B19: Sven | C19: Mühlen | D19: sven@dpsgwegberg.de | E19: +4917696819125 | F19: DPSG Wegberg | G19: Germany | H19: Deutsche Pfadfinderschaft Sankt Georg | I19: DPSG Wegberg | J19: 0001041000 | K19: Wegberg | L19: 30 | M19: 6 | N19: Friday | O19: 18:00 - 21:00 | P19: Monday | Q19: 09:00 - 12:00 | R19: 0 | S19: IST-46593 | T19: 900 | U19: Mollie | V19: 2024-12-02 20:03:36 | W19: 1733169816 | X19: 0 | Y19: 0 | Z19: 2
A20: 21 | B20: Des | C20: Mahon | D20: des.mahon@arrowscouts.org.uk | E20: +447809149414 | F20: Des Mahon 3rd Chandlers Ford Scouts Arrow District | G20: GB | H20: British Guides In Foreign Countrys | I20: 3rd Chandler’s Ford | J20: 3rd | K20: Chandler’s Ford | L20: 6 | M20: 2 | N20: Friday | O20: 15:00 - 18:00 | P20: Monday | Q20: 09:00 - 12:00 | R20: Partnering with 1st Prague Scouts as we are sharing equipment | S20: IST-11133 | T20: 200 | U20: Mollie | V20: 2024-11-30 23:26:03 | W20: 1733009163 | X20: 0 | Y20: 0 | Z20: 2
A21: 17 | B21: Christopher | C21: Wait | D21: waitchris0103@gmail.com | E21: +420777216228 | F21: 1st Prague (Czech Republic) Scout Group z.s. – British Scouting Overseas Pod pekárnami 251/4, Vysočany, 190 00 Praha 9 ICO: 04755057 | G21: GB | H21: BSO | I21: 1st Prague Scouts | J21: 04755057 | K21: Prague | L21: 29 | M21: 6 | N21: Friday | O21: 09:00 - 12:00 | P21: Monday | Q21: 12:00 - 15:00 | R21: 0 | S21: IST-11133 | T21: 875 | U21: Mollie | V21: 2024-11-30 23:10:31 | W21: 1733008231 | X21: 0 | Y21: 0 | Z21: 2
A22: 49 | B22: Zuzana | C22: Holekova | D22: zuzanaholekova@centrum.sk | E22: +421905886516 | F22: 0 | G22: Slovakia | H22: Choose... | I22: Zbor Irmy Ševcechovej | J22: 31 | K22: Trenčianska Teplá | L22: 2 | M22: 1 | N22: Friday | O22: 15:00 - 18:00 | P22: Monday | Q22: 12:00 - 15:00 | R22: 0 | S22: IST-35004 | T22: 75 | U22: Mollie | V22: 2024-12-08 13:07:16 | W22: 1733663236 | X22: 0 | Y22: 0 | Z22: 2
A23: 44 | B23: Zuzana | C23: Holekova | D23: zuzanaholekova@centrum.sk | E23: +421905886516 | F23: 0 | G23: Slovakia | H23: Guests | I23: zbor Irmy Ševcechovej | J23: 31 | K23: Trenčianska Teplá | L23: 5 | M23: 1 | N23: Friday | O23: 15:00 - 18:00 | P23: Monday | Q23: 12:00 - 15:00 | R23: 0 | S23: IST-10569 | T23: 150 | U23: Mollie | V23: 2024-12-07 19:33:48 | W23: 1733600028 | X23: 0 | Y23: 0 | Z23: 2
A24: 96 | B24: Michał | C24: Wnuk | D24: michal.wnuk@zhp.net.pl | E24: +48602672459 | F24: 0 | G24: Poland | H24: Zwiazek Harcerstwa Polskiego | I24: Zawiercie 1 | J24: 1 | K24: Zawiercie | L24: 13 | M24: 2 | N24: Friday | O24: 15:00 - 18:00 | P24: Monday | Q24: 09:00 - 12:00 | R24: We ask that the camping area for the patrol "zawiercie 1" and "zawiercie 2" be next to each other. We are the same large group from one city. Would it be possible for us to spend the night on Thursday at the convention site? | S24: IST-63079 | T24: 375 | U24: Mollie | V24: 2025-02-05 14:21:53 | W24: 1738765313 | X24: 0 | Y24: 0 | Z24: 2
A25: 97 | B25: Katarzyna | C25: Krzepkowska | D25: hufiec@zawiercie.zhp.pl | E25: +48602672459 | F25: 0 | G25: Poland | H25: Zwiazek Harcerstwa Polskiego | I25: Zawiercie 2 | J25: 2 | K25: Zawiercie | L25: 13 | M25: 2 | N25: Friday | O25: 15:00 - 18:00 | P25: Monday | Q25: 09:00 - 12:00 | R25: We ask that the camping area for the patrol "zawiercie 1" and "zawiercie 2" be next to each other. We are the same large group from one city. Would it be possible for us to spend the night on Thursday at the convention site? | S25: IST-10147 | T25: 375 | U25: Mollie | V25: 2025-02-05 14:25:33 | W25: 1738765533 | X25: 0 | Y25: 0 | Z25: 2
A26: 98 | B26: Jacek | C26: Słaby | D26: jacek.slaby@zhp.net.pl | E26: +48502039396 | F26: 0 | G26: Poland | H26: Zwiazek Harcerstwa Polskiego | I26: 30 WDH | J26: 30 | K26: Warszawa | L26: 7 | M26: 1 | N26: Friday | O26: 15:00 - 18:00 | P26: Monday | Q26: 09:00 - 12:00 | R26: 0 | S26: IST-19825 | T26: 200 | U26: Mollie | V26: 2025-02-05 14:30:41 | W26: 1738765842 | X26: 0 | Y26: 0 | Z26: 2
A27: 99 | B27: Marta | C27: Zielińska | D27: marta.zielinska@zhp.net.pl | E27: +48535775774 | F27: 0 | G27: Poland | H27: Zwiazek Harcerstwa Polskiego | I27: 424 DS "Żywioły" | J27: 424 | K27: Izabelin | L27: 13 | M27: 2 | N27: Friday | O27: 18:00 - 21:00 | P27: Monday | Q27: 09:00 - 12:00 | R27: 0 | S27: IST-11217 | T27: 375 | U27: Mollie | V27: 2025-02-05 15:33:27 | W27: 1738769607 | X27: 0 | Y27: 0 | Z27: 2
A28: 108 | B28: Michał | C28: Święcicki | D28: michal.swiecicki@zhp.net.pl | E28: +48511267708 | F28: 0 | G28: Poland | H28: Zwiazek Harcerstwa Polskiego | I28: Granda | J28: 420 | K28: Warszawa | L28: 8 | M28: 2 | N28: Friday | O28: 18:00 - 21:00 | P28: Monday | Q28: 09:00 - 12:00 | R28: 0 | S28: IST-20570 | T28: 250 | U28: Mollie | V28: 2025-02-16 21:37:27 | W28: 1739741847 | X28: 0 | Y28: 0 | Z28: 2
A29: 109 | B29: Julia | C29: Kinderman | D29: julia.kinderman@zhp.net.pl | E29: +48519656858 | F29: 0 | G29: Poland | H29: Zwiazek Harcerstwa Polskiego | I29: Gwardians | J29: 96 | K29: Łódź | L29: 14 | M29: 2 | N29: Friday | O29: 12:00 - 15:00 | P29: Monday | Q29: 09:00 - 12:00 | R29: 0 | S29: IST-18637 | T29: 400 | U29: Mollie | V29: 2025-02-16 21:41:39 | W29: 1739742099 | X29: 0 | Y29: 0 | Z29: 2
A30: 115 | B30: Patrycja | C30: Kiryluk | D30: patrycja.kiryluk@zhp.net.pl | E30: +48 604948623 | F30: 0 | G30: Poland | H30: Zwiazek Harcerstwa Polskiego | I30: FDDH 2 | J30: 2 | K30: Morąg | L30: 15 | M30: 2 | N30: Friday | O30: 09:00 - 12:00 | P30: Monday | Q30: 09:00 - 12:00 | R30: We would be grateful if you could place our two teams, FDDH 1 and FDDH 2, in the same subcamp during the Intercamp. We don’t have enough equipment to divide between the teams, and we are part of the same scout group. | S30: IST-83825 | T30: 400 | U30: Mollie | V30: 2025-02-23 18:34:30 | W30: 1740335670 | X30: Plus 1 to pay | Y30: 0 | Z30: 2
A31: 116 | B31: Kamil | C31: Sagan | D31: kamil.sagan@zhp.net.pl | E31: +48795599749 | F31: 0 | G31: Poland | H31: Zwiazek Harcerstwa Polskiego | I31: HSDeserterzy | J31: 9 | K31: Kraków | L31: 10 | M31: 2 | N31: Friday | O31: 18:00 - 21:00 | P31: Monday | Q31: 09:00 - 12:00 | R31: 0 | S31: IST-16632 | T31: 300 | U31: Mollie | V31: 2025-02-23 18:38:33 | W31: 1740335913 | X31: 0 | Y31: 0 | Z31: 2
A32: 117 | B32: Jakub | C32: Jędras | D32: jakub.jedras@zhp.net.pl | E32: +48606891044 | F32: 0 | G32: Poland | H32: Zwiazek Harcerstwa Polskiego | I32: HSDeserterki | J32: 9 | K32: Kraków | L32: 5 | M32: 1 | N32: Friday | O32: 15:00 - 18:00 | P32: Monday | Q32: 09:00 - 12:00 | R32: 0 | S32: IST-17214 | T32: 150 | U32: Mollie | V32: 2025-02-23 18:44:55 | W32: 1740336295 | X32: 0 | Y32: 0 | Z32: 2
A33: 119 | B33: Dominik Jeffrey | C33: Rimaszauskas | D33: dominik.rimaszauskas@zhp.net.pl | E33: +48535037130 | F33: 0 | G33: Poland | H33: Zwiazek Harcerstwa Polskiego | I33: FDDH 1 | J33: 8 | K33: MORĄG | L33: 15 | M33: 2 | N33: Friday | O33: 15:00 - 18:00 | P33: Monday | Q33: 09:00 - 12:00 | R33: 0 | S33: IST-33514 | T33: 425 | U33: Mollie | V33: 2025-02-23 18:53:04 | W33: 1740336784 | X33: 0 | Y33: 0 | Z33: 2
A34: 136 | B34: Katarzyna | C34: Kwiatkowska | D34: katarzyna.kwiatkowska@zhp.net.pl | E34: +48 502601077 | F34: 0 | G34: Poland | H34: Zwiazek Harcerstwa Polskiego | I34: Włóczykije 1 | J34: 30 WDH | K34: Warszawa | L34: 7 | M34: 2 | N34: Friday | O34: 15:00 - 18:00 | P34: Monday | Q34: 09:00 - 12:00 | R34: 0 | S34: 0 | T34: 0 | U34: 0 | V34: 0 | W34: 0 | X34: 225 euro to be paid | Y34: 225 | Z34: 2
A35: 2 | B35: Frans | C35: Lenders | D35: franslenders@home.nl | E35: +31621857140 | F35: 0 | G35: The Netherlands | H35: Scouting Nederland | I35: St. Rumoldus | J35: 1454 | K35: Weert | L35: 16 | M35: 4 | N35: Friday | O35: 12:00 - 15:00 | P35: Monday | Q35: 12:00 - 15:00 | R35: 0 | S35: IST-75688 | T35: 500 | U35: Mollie | V35: 2024-11-30 19:07:13 | W35: 1732993633 | X35: 0 | Y35: 0 | Z35: 2
A36: 3 | B36: Arno | C36: van As | D36: arno.van.as@hotmail.com | E36: +31628679230 | F36: 0 | G36: The Netherlands | H36: Scouting Nederland | I36: Scouting Ewijk | J36: 1228 | K36: Ewijk | L36: 18 | M36: 5 | N36: Friday | O36: 12:00 - 15:00 | P36: Monday | Q36: 12:00 - 15:00 | R36: 0 | S36: IST-97382 | T36: 575 | U36: Mollie | V36: 2024-11-30 19:11:58 | W36: 1732993918 | X36: 0 | Y36: 0 | Z36: 2
A37: 4 | B37: Ricardo | C37: Laurens | D37: r.laurens.1995@gmail.com | E37: +31621642397 | F37: 0 | G37: The Netherlands | H37: Scouting Nederland | I37: St.Scouting Saffatin Maurik | J37: 1215 | K37: Maurik | L37: 12 | M37: 3 | N37: Friday | O37: 12:00 - 15:00 | P37: Monday | Q37: 12:00 - 15:00 | R37: 0 | S37: IST-85959 | T37: 375 | U37: Mollie | V37: 2024-11-30 19:14:24 | W37: 1732994065 | X37: 0 | Y37: 0 | Z37: 2
A38: 8 | B38: Peter | C38: de Graag | D38: peterdegraag@hotmail.com | E38: +31683644415 | F38: 0 | G38: The Netherlands | H38: Scouting Nederland | I38: Marnix van Sint Aldegonde | J38: 2085 | K38: Vlaardingen | L38: 5 | M38: 2 | N38: Friday | O38: 12:00 - 15:00 | P38: Monday | Q38: 12:00 - 15:00 | R38: 0 | S38: IST-15785 | T38: 175 | U38: Mollie | V38: 2024-11-30 19:45:35 | W38: 1732995935 | X38: 0 | Y38: 0 | Z38: 2
A39: 9 | B39: Frans | C39: Nieuwenhuys | D39: f.nieuwenhuys@gmail.com | E39: +31646337186 | F39: 0 | G39: The Netherlands | H39: Scouting Nederland | I39: Scouting St. Martinus | J39: 1606 | K39: Zaltbommel | L39: 7 | M39: 3 | N39: Friday | O39: 12:00 - 15:00 | P39: Monday | Q39: 12:00 - 15:00 | R39: 0 | S39: IST-21266 | T39: 250 | U39: Mollie | V39: 2024-11-30 19:48:36 | W39: 1732996116 | X39: 0 | Y39: 0 | Z39: 2
A40: 12 | B40: Joey | C40: Gelissen | D40: joeygelissen@outlook.com | E40: +31645816844 | F40: 0 | G40: The Netherlands | H40: Scouting Nederland | I40: Scouting St. Martinus Beek | J40: 1415 | K40: Beek (L) | L40: 29 | M40: 6 | N40: Friday | O40: 15:00 - 18:00 | P40: Monday | Q40: 12:00 - 15:00 | R40: 0 | S40: IST-10208 | T40: 875 | U40: Mollie | V40: 2024-11-30 19:59:14 | W40: 1732996754 | X40: 0 | Y40: 0 | Z40: 2
A41: 53 | B41: Sofie | C41: Tijssen | D41: sofietijssen@hotmail.com | E41: +31612305045 | F41: 0 | G41: The Netherlands | H41: Scouting Nederland | I41: Scouting Johannes Vianney | J41: 1540 | K41: Eindhoven | L41: 34 | M41: 7 | N41: Friday | O41: 12:00 - 15:00 | P41: Monday | Q41: 12:00 - 15:00 | R41: 0 | S41: IST-65379 | T41: 1025 | U41: Mollie | V41: 2024-12-20 13:01:11 | W41: 1734699671 | X41: 0 | Y41: 0 | Z41: 2
A42: 27 | B42: Mattie | C42: Coolen | D42: mattie.coolen@bluewin.ch | E42: +41792585330 | F42: 0 | G42: United States | H42: Boy Scouts of America - Transatlantic Council | I42: Troop 681 Basel | J42: 0681 | K42: Basel | L42: 15 | M42: 5 | N42: Friday | O42: 18:00 - 21:00 | P42: Monday | Q42: 09:00 - 12:00 | R42: We have 4 Adults signed up as we need drivers for our scouts and the equipment. We have one additional Adult, Andrew Wright <andrewwright675@btinternet.com>. For the past two Intercamps, Andrew served in the TAC trading post. At the moment it is not clear that the trading post will be at Intercamp or if he will be asked to serve. However, he would like to attend the event and we are willing to host him. He will be traveling from and to Basel with us. | S42: IST-19768 | T42: 500 | U42: Mollie | V42: 2024-12-01 10:01:44 | W42: 1733047304 | X42: 1 | Y42: Payment link sent | Z42: 2
A43: 32 | B43: Alyson | C43: Thompson | D43: alysonmthompson@gmail.com | E43: +1 | F43: 0 | G43: United States | H43: Boy Scouts of America - Transatlantic Council | I43: 1920G- Boy Scouts of America | J43: 1920G | K43: Ramstein AB | L43: 15 | M43: 3 | N43: Friday | O43: 18:00 - 21:00 | P43: Monday | Q43: 12:00 - 15:00 | R43: This is a female troop, so I am requesting attendance for the scoutmaster (male), assistant scoutmaster (male), and a female adult. | S43: IST-64029 | T43: 300 | U43: Mollie | V43: 2024-12-01 18:15:56 | W43: 1733076956 | X43: Need to pay for 6 extra scouts | Y43: 0 | Z43: 2
A44: 43 | B44: Joshua | C44: Gartner | D44: jpgartner@gmail.com | E44: +491756066993 | F44: 0 | G44: United States | H44: Boy Scouts of America - Transatlantic Council | I44: Wiesbaden Troop | J44: Troop 107 | K44: Wiesbaden | L44: 25 | M44: 5 | N44: Friday | O44: 15:00 - 18:00 | P44: Monday | Q44: 09:00 - 12:00 | R44: 0 | S44: IST-17338 | T44: 750 | U44: Mollie | V44: 2024-12-07 17:40:24 | W44: 1733593224 | X44: 0 | Y44: 0 | Z44: 2
A45: 51 | B45: Steven | C45: Harker | D45: charker22@gmail.com | E45: +49 | F45: Troop 240 B Intercamp Registration | G45: United States | H45: Boy Scouts of America - Transatlantic Council | I45: Troop 240 | J45: 240 | K45: Grafenwoehr | L45: 13 | M45: 3 | N45: Friday | O45: 18:00 - 21:00 | P45: Monday | Q45: 09:00 - 12:00 | R45: We need two male leaders for our male scouts and one female leader for our Female scouts. | S45: IST-19596 | T45: 400 | U45: Mollie | V45: 2024-12-11 21:24:46 | W45: 1733952286 | X45: 0 | Y45: 0 | Z45: 2
A46: 126 | B46: JASON | C46: MUELLER | D46: jmueller6002@yahoo.com | E46: +4915209233692 | F46: 0 | G46: United States | H46: Boy Scouts of America - Transatlantic Council | I46: 303 | J46: 0303 | K46: Hohenfels | L46: 8 | M46: 3 | N46: Friday | O46: 12:00 - 15:00 | P46: Monday | Q46: 12:00 - 15:00 | R46: 0 | S46: IST-40890 | T46: 275 | U46: Mollie | V46: 2025-02-27 18:28:15 | W46: 1740680895 | X46: 0 | Y46: 0 | Z46: 2
A47: 31 | B47: Sarah | C47: Parks | D47: parks.sarah@gmail.com | E47: +4915151847115 | F47: 0 | G47: United States | H47: Girl Scouts of the USA | I47: Girl Scouts of the USA | J47: Stuttgart | K47: Stuttgart | L47: 34 | M47: 7 | N47: Friday | O47: 15:00 - 18:00 | P47: Sunday | Q47: 15:00 - 18:00 | R47: Bus arrives Sunday 17:30; camp needs to be close to road | S47: IST-87889 | T47: 1025 | U47: Mollie | V47: 2024-12-01 13:57:29 | W47: 1733061449 | X47: 0 | Y47: 0 | Z47: 2
A48: 50 | B48: Helen | C48: Thurston | D48: helen.thurston2@gmail.com | E48: +41789765569 | F48: Please send the invoice to be paid to: Jonathon Hopkins, USAGSO - Basel Treasurer, Schaienweg 2 Ettingen CH-4107 Switzerland | G48: United States | H48: Girl Scouts of the USA | I48: White Roses / USA girl scouts overseas | J48: 38738 | K48: Basel | L48: 6 | M48: 2 | N48: Friday | O48: 18:00 - 21:00 | P48: Monday | Q48: 12:00 - 15:00 | R48: We have not planned how we will get there yet but will let you know if anything changes from what I have estimated above. I hope that is okay. Kind regards Helen | S48: IST-19969 | T48: 200 | U48: Mollie | V48: 2024-12-08 16:22:24 | W48: 1733674944 | X48: 0 | Y48: 0 | Z48: 2
L58: =SUM(L2:L49) -> 685 | M58: =SUM(M2:M49) -> 152 | N58: =L58+M58 -> 837

Sheet Subcamp 3
A1: No | B1: First name | C1: Last name | D1: Email | E1: Mobile phone | F1: Invoice details | G1: Country | H1: Scout Association | I1: Troop name | J1: Troop organisation number | K1: City | L1: Number of Children | M1: Number of Leaders | N1: Arrival day | O1: Arrival time | P1: Departure day | Q1: Departure time | R1: Further remarks (optional) | S1: Order Number | T1: Total Costs | U1: Payment Type | V1: Registration time | W1: Order Number2 | X1: Additional registrants | Y1: Comments RJ: | Z1: Subcamp
A2: {=_xlfn._xlws.FILTER('All Subcamps'!A2:Z139,'All Subcamps'!Z2:Z139=3)} -> 60 | B2: Martin | C2: Kolarik | D2: smurf@skaut.cz | E2: +420723923943 | F2: Junák – český skaut, středisko Járy Kaštila Prostějov, z. s. Sokolská 30, 796 01 Prostějov Czech republic IČO: 65762959 | G2: Czech Republic | H2: JUNAK - cesky skaut | I2: JK | J2: 713.05 | K2: Prostejov | L2: 20 | M2: 4 | N2: Friday | O2: 15:00 - 18:00 | P2: Monday | Q2: 09:00 - 12:00 | R2: 0 | S2: IST-11762 | T2: 600 | U2: Mollie | V2: 2025-01-15 07:08:46 | W2: 1736924926 | X2: 0 | Y2: 0 | Z2: 3
A3: 61 | B3: Pavel | C3: Šenkyřík | D3: 180.veneta@gmail.com | E3: +420733233486 | F3: Customer: Junák - český skaut, středisko Platan Praha, z. s. Adress: Viktorinova 1122/1,Praha 4 – Nusle, 140 00 Praha, Česká Republika IČO: 40613593 | G3: Czech Republic | H3: JUNAK - cesky skaut | I3: Platan | J3: 114.32 | K3: Prague | L3: 20 | M3: 3 | N3: Friday | O3: 18:00 - 21:00 | P3: Monday | Q3: 09:00 - 12:00 | R3: 0 | S3: IST-32540 | T3: 575 | U3: Mollie | V3: 2025-01-18 14:39:42 | W3: 1737211182 | X3: 0 | Y3: 0 | Z3: 3
A4: 70 | B4: Dana | C4: Tarantová | D4: komtesa.dana@gmail.com | E4: +420606227817 | F4: Junák - český skaut, středisko Oheň Most, z. s. Slovenského národního povstání 1191 434 01 Most IČ: 41324919 | G4: Czech Republic | H4: JUNAK - cesky skaut | I4: Junák - český skaut, středisko Oheň Most, z. s. | J4: 42501 | K4: Most | L4: 20 | M4: 4 | N4: Friday | O4: 15:00 - 18:00 | P4: Monday | Q4: 09:00 - 12:00 | R4: 0 | S4: IST-15385 | T4: 600 | U4: Mollie | V4: 2025-01-26 18:36:08 | W4: 1737916569 | X4: 0 | Y4: 0 | Z4: 3
A5: 71 | B5: Ondřej | C5: Mikulčík | D5: ondrej.mikulcik@gmail.com | E5: +420702282329 | F5: Junák Český skaut - středisko Vizovice z.s. Razov 761 Vizovice 76312 Czech republic IC: 46277404 | G5: Czech Republic | H5: JUNAK - cesky skaut | I5: Vizovice | J5: 724.12 | K5: Vizovice | L5: 13 | M5: 2 | N5: Friday | O5: 09:00 - 12:00 | P5: Monday | Q5: 09:00 - 12:00 | R5: 0 | S5: IST-29006 | T5: 375 | U5: Mollie | V5: 2025-01-28 16:33:49 | W5: 1738082029 | X5: 0 | Y5: 0 | Z5: 3
A6: 73 | B6: Jonáš | C6: Novotný | D6: novotny.jonas@seznam.cz | E6: +420731403977 | F6: 0 | G6: Czech Republic | H6: JUNAK - cesky skaut | I6: Anikrok a Dvojka | J6: 532.08 | K6: Přelouč | L6: 14 | M6: 4 | N6: Friday | O6: 12:00 - 15:00 | P6: Monday | Q6: 09:00 - 12:00 | R6: 0 | S6: IST-95252 | T6: 450 | U6: Mollie | V6: 2025-01-28 19:30:24 | W6: 1738092624 | X6: 0 | Y6: 0 | Z6: 3
A7: 75 | B7: Agáta | C7: Navrkalová | D7: agata.nvr@skaut.cz | E7: +420773301941 | F7: 0 | G7: Czech Republic | H7: JUNAK - cesky skaut | I7: Junák - český skaut, středisko Podyjí Znojmo, z. s. | J7: 627.02 | K7: Znojmo | L7: 8 | M7: 2 | N7: Friday | O7: 09:00 - 12:00 | P7: Monday | Q7: 12:00 - 15:00 | R7: 0 | S7: IST-18787 | T7: 250 | U7: Mollie | V7: 2025-01-31 10:36:55 | W7: 1738319816 | X7: 0 | Y7: 0 | Z7: 3
A8: 83 | B8: Kateřina | C8: Tuháčková | D8: katy58@skaut.cz | E8: +420725882920 | F8: 0 | G8: Czech Republic | H8: JUNAK - cesky skaut | I8: Sluneční údolí | J8: 323.05.058 | K8: Starý Plzenec | L8: 8 | M8: 1 | N8: Friday | O8: 15:00 - 18:00 | P8: Monday | Q8: 09:00 - 12:00 | R8: 0 | S8: IST-11470 | T8: 225 | U8: Mollie | V8: 2025-02-03 20:18:05 | W8: 1738613885 | X8: 0 | Y8: 0 | Z8: 3
A9: 105 | B9: Kateřina | C9: Čechová | D9: albus@skaut.cz | E9: +420602144407 | F9: Junák – český skaut, středisko Bílý los Praha, z. s. , Praha Liborova 470/2, Praha 6 – Břevnov, 16900 IČ: 61389650 | G9: Czech Republic | H9: JUNAK - cesky skaut | I9: Bílý los | J9: 116.33 | K9: Prague | L9: 6 | M9: 1 | N9: Friday | O9: 15:00 - 18:00 | P9: Monday | Q9: 12:00 - 15:00 | R9: Hello, we are not sure about out arrival and departure time, but I think we will be flexible about that. We are going to order bus with another few troops form our area. Greets, Katka Čechová - Albus. | S9: IST-15861 | T9: 175 | U9: Mollie | V9: 2025-02-10 18:13:21 | W9: 1739211201 | X9: 0 | Y9: 0 | Z9: 3
A10: 106 | B10: Miroslav | C10: Král | D10: usteckadvojka@gmail.com | E10: +420605567227 | F10: 0 | G10: Czech Republic | H10: JUNAK - cesky skaut | I10: Ústecká dvojka | J10: 427.01.002 | K10: Ústí nad Labem | L10: 20 | M10: 4 | N10: Friday | O10: 15:00 - 18:00 | P10: Monday | Q10: 09:00 - 12:00 | R10: 0 | S10: IST-21250 | T10: 600 | U10: Mollie | V10: 2025-02-11 16:48:31 | W10: 1739292511 | X10: 0 | Y10: 0 | Z10: 3
A11: 130 | B11: Mikuláš | C11: Jandík | D11: jandik.mikulasz@gmail.com | E11: +420731743330 | F11: Junák - český skaut, Středisko bratří Mašínů Praha z. s., Čihákova 1791/20, Praha 9, 190 00 | G11: Czech Republic | H11: JUNAK - cesky skaut | I11: Ginkgo | J11: 112.53 | K11: Praha | L11: 13 | M11: 2 | N11: Friday | O11: 18:00 - 21:00 | P11: Monday | Q11: 09:00 - 12:00 | R11: It is possible that we will arrive at a different time (during Friday afternoon or evening). | S11: IST-18827 | T11: 375 | U11: Mollie | V11: 2025-03-20 17:00:41 | W11: 1742490041 | X11: 0 | Y11: 0 | Z11: 3
A12: 58 | B12: POGGIO | C12: STEPHAN | D12: poggio.stephan@yahoo.com | E12: +33632153653 | F12: 0 | G12: France | H12: Scoutisme Français | I12: Scout du Florival | J12: EEDF - GUEBWILLER - SCOUTS DU FLORIVAL - 706019 | K12: Guebwiller - Soultz | L12: 21 | M12: 4 | N12: Friday | O12: 12:00 - 15:00 | P12: Monday | Q12: 09:00 - 12:00 | R12: 0 | S12: IST-13515 | T12: 625 | U12: Mollie | V12: 2025-01-12 17:15:12 | W12: 1736702112 | X12: 0 | Y12: 0 | Z12: 3
A13: 25 | B13: Daniela | C13: Kouril | D13: daniela@cityscouts.org | E13: +491605807584 | F13: Falls Julia vom Dorp dieses Jahr in einem Subcampteam ist, möchten wir gerne in ihr Subcamp. Sie ist Leiterin in unserem Stamm. | G13: Germany | H13: Deutsche Pfadfinderschaft Sankt Georg | I13: Stamm Cityscouts | J13: 010304 | K13: Mönchengladbach | L13: 27 | M13: 6 | N13: Friday | O13: 12:00 - 15:00 | P13: Monday | Q13: 12:00 - 15:00 | R13: 0 | S13: IST-11133 | T13: 825 | U13: Mollie | V13: 2024-12-01 00:21:33 | W13: 1733012493 | X13: 0 | Y13: 0 | Z13: 3
A14: 26 | B14: Jan | C14: Van den Brakel | D14: jbrl@cbs.nl | E14: +31 | F14: I will pay via banktransfer. | G14: Germany | H14: Deutsche Pfadfinderschaft Sankt Georg | I14: St Nikolaus Gangelt | J14: 010403 | K14: Gangelt | L14: 12 | M14: 4 | N14: Friday | O14: 12:00 - 15:00 | P14: Monday | Q14: 12:00 - 15:00 | R14: WE need four leaders for transportation. | S14: IST-41645 | T14: 400 | U14: Mollie | V14: 2024-12-01 09:32:32 | W14: 1733045552 | X14: 0 | Y14: 0 | Z14: 3
A15: 28 | B15: Katharina | C15: Wenderott | D15: k.wenderott@paderborn.com | E15: +4915750634181 | F15: Pastoralbüro An St. Marien DPSG Phönix Bonn Heerstraße 128 53111 Bonn lea@dpsg-phoenix.net | G15: Germany | H15: Deutsche Pfadfinderschaft Sankt Georg | I15: DPSG Phönix Bonn | J15: 10/12/03 | K15: Bonn | L15: 26 | M15: 6 | N15: Friday | O15: 18:00 - 21:00 | P15: Monday | Q15: 09:00 - 12:00 | R15: 0 | S15: IST-13423 | T15: 800 | U15: Mollie | V15: 2024-12-01 12:09:38 | W15: 1733054978 | X15: 0 | Y15: 0 | Z15: 3
A16: 29 | B16: Sarah | C16: Corres | D16: corres.sarah@gmx.de | E16: +491754170858 | F16: 0 | G16: Germany | H16: Deutsche Pfadfinderschaft Sankt Georg | I16: Pfadfinder Erkelenz | J16: 010413 | K16: Erkelenz | L16: 25 | M16: 5 | N16: Friday | O16: 15:00 - 18:00 | P16: Monday | Q16: 09:00 - 12:00 | R16: 0 | S16: IST-17411 | T16: 750 | U16: Mollie | V16: 2024-12-01 12:15:33 | W16: 1733055333 | X16: 0 | Y16: 0 | Z16: 3
A17: 34 | B17: Svenja | C17: Walter | D17: svenjawalter95@web.de | E17: +491741021155 | F17: 0 | G17: Germany | H17: Deutsche Pfadfinderschaft Sankt Georg | I17: DPSG Obertürkheim Stamm St. Franziskus | J17: 19/01/01 | K17: Stuttgart | L17: 5 | M17: 3 | N17: Friday | O17: 12:00 - 15:00 | P17: Monday | Q17: 12:00 - 15:00 | R17: 0 | S17: IST-10640 | T17: 200 | U17: Mollie | V17: 2024-12-02 10:28:28 | W17: 1733135308 | X17: 0 | Y17: 0 | Z17: 3
A18: 39 | B18: Fabian | C18: Dietzmann | D18: fabian.dietzmann@gmail.com | E18: +4917643431461 | F18: 0 | G18: Germany | H18: Deutsche Pfadfinderschaft Sankt Georg | I18: Stamm von Berg | J18: 0010010100 | K18: Solingen | L18: 22 | M18: 5 | N18: Friday | O18: 15:00 - 18:00 | P18: Monday | Q18: 09:00 - 12:00 | R18: 0 | S18: IST-31582 | T18: 675 | U18: Mollie | V18: 2024-12-02 21:07:13 | W18: 1733173633 | X18: 0 | Y18: 0 | Z18: 3
A19: 46 | B19: Annika | C19: Tobies | D19: an@tobies.info | E19: +4915734650329 | F19: DPSG St. Rochus Rochusstraße 223 53123 Bonn Germany | G19: Germany | H19: Deutsche Pfadfinderschaft Sankt Georg | I19: DPSG St. Rochus | J19: Pfadfinder | K19: Bonn | L19: 9 | M19: 3 | N19: Friday | O19: 15:00 - 18:00 | P19: Monday | Q19: 12:00 - 15:00 | R19: Hello, we've got two boys in our troop that have diagnosis in the field of adhd and autism that we want to include in our group activities. To do this we need to increase the number of leaders. We are looking forward to this Intercamp! Cheers Annika | S19: IST-17682 | T19: 300 | U19: Mollie | V19: 2024-12-07 20:38:29 | W19: 1733603909 | X19: 0 | Y19: 0 | Z19: 3
A20: 16 | B20: Vladimir | C20: Bilek | D20: v.bilek@email.cz | E20: +352621277044 | F20: same as above | G20: Luxembourg | H20: Guests | I20: Telstar scouts international | J20: 12345 | K20: Luxembourg | L20: 30 | M20: 5 | N20: Friday | O20: 18:00 - 21:00 | P20: Monday | Q20: 09:00 - 12:00 | R20: 0 | S20: IST-23477 | T20: 875 | U20: Mollie | V20: 2024-11-30 23:10:24 | W20: 1733008224 | X20: 0 | Y20: 0 | Z20: 3
A21: 139 | B21: András | C21: Imregh | D21: 0 | E21: 0 | F21: 0 | G21: Hungary | H21: Magyar Cserkészszövetség | I21: 0 | J21: 0 | K21: Budapest | L21: 12 | M21: 5 | N21: Friday | O21: 15:00 - 18:00 | P21: Monday | Q21: 09:00 - 12:00 | R21: 0 | S21: 0 | T21: 0 | U21: 0 | V21: 0 | W21: 0 | X21: 575 euro to be paid | Y21: 575 | Z21: 3
A22: 84 | B22: Aleksandra | C22: Comblik | D22: aleksandra.comblik@zhp.net.pl | E22: +48510361821 | F22: 0 | G22: Poland | H22: Zwiazek Harcerstwa Polskiego | I22: Silva | J22: 76 | K22: Gdansk | L22: 13 | M22: 1 | N22: Friday | O22: 12:00 - 15:00 | P22: Monday | Q22: 09:00 - 12:00 | R22: 0 | S22: IST-12664 | T22: 350 | U22: Mollie | V22: 2025-02-04 14:27:42 | W22: 1738679262 | X22: 0 | Y22: 0 | Z22: 3
A23: 90 | B23: Joanna | C23: Poniatowska | D23: joanna.poniatowska@zhp.net.pl | E23: +48509069268 | F23: 0 | G23: Poland | H23: Zwiazek Harcerstwa Polskiego | I23: 13 WDH - patrol harcerski | J23: 13 | K23: Złotokłos | L23: 15 | M23: 2 | N23: Friday | O23: 18:00 - 21:00 | P23: Monday | Q23: 09:00 - 12:00 | R23: 0 | S23: IST-12701 | T23: 425 | U23: Mollie | V23: 2025-02-05 12:35:14 | W23: 1738758914 | X23: 0 | Y23: 0 | Z23: 3
A24: 91 | B24: Oskar | C24: Kostyrka | D24: oskar.kostyrka@zhp.net.pl | E24: +48535003542 | F24: 0 | G24: Poland | H24: Zwiazek Harcerstwa Polskiego | I24: 13WDH patrol starszoharcerski | J24: 13 | K24: Złotokłos | L24: 14 | M24: 2 | N24: Friday | O24: 15:00 - 18:00 | P24: Monday | Q24: 09:00 - 12:00 | R24: 0 | S24: IST-17219 | T24: 400 | U24: Mollie | V24: 2025-02-05 12:37:30 | W24: 1738759050 | X24: 0 | Y24: 0 | Z24: 3
A25: 93 | B25: Nikola | C25: Mulewska | D25: nikola.mulewska@zhp.net.pl | E25: +48505834404 | F25: 0 | G25: Poland | H25: Zwiazek Harcerstwa Polskiego | I25: 71N | J25: 71 | K25: Gdańsk | L25: 8 | M25: 1 | N25: Friday | O25: 15:00 - 18:00 | P25: Monday | Q25: 09:00 - 12:00 | R25: In there is an option we wolud like to be togeter with 71A, 76 Silva, 74 GDH „Kotwice”, 78 Dianthus and when still tehre is posibility we would like to be also with 98 Płomienne zorze, 94 GDSH ,,Venga, vamos!", Nebula. Thank you! | S25: IST-17468 | T25: 225 | U25: Mollie | V25: 2025-02-05 14:07:06 | W25: 1738764426 | X25: 0 | Y25: 0 | Z25: 3
A26: 94 | B26: Adrianna | C26: Gutowska | D26: adrianna.gutowska@zhp.net.pl | E26: +48780121856 | F26: 0 | G26: Poland | H26: Zwiazek Harcerstwa Polskiego | I26: 71 A | J26: 71 | K26: Gdańsk | L26: 7 | M26: 2 | N26: Friday | O26: 12:00 - 15:00 | P26: Monday | Q26: 09:00 - 12:00 | R26: We are together with 71 N so the amount of children is 15 and we have 3 leaders. So proportions are Preserved. | S26: IST-11512 | T26: 225 | U26: Mollie | V26: 2025-02-05 14:14:47 | W26: 1738764887 | X26: 0 | Y26: 0 | Z26: 3
A27: 95 | B27: Zuzanna | C27: Stankiewicz | D27: zuzanna.stankiewicz1@zhp.net.pl | E27: +48535225116 | F27: 0 | G27: Poland | H27: Zwiazek Harcerstwa Polskiego | I27: Płomienne Zorze | J27: 98 | K27: Gdańsk | L27: 7 | M27: 1 | N27: Friday | O27: 12:00 - 15:00 | P27: Monday | Q27: 09:00 - 12:00 | R27: In there is an option we wolud like to be togeter with 71A, 71N, 76 Silva, 74 GDH „Kotwice”, 78 Dianthus and when still tehre is posibility we would like to be also with, 94 GDSH ,,Venga, vamos!", Nebula. Thank you! | S27: IST-20772 | T27: 200 | U27: Mollie | V27: 2025-02-05 14:19:18 | W27: 1738765158 | X27: 0 | Y27: 0 | Z27: 3
A28: 107 | B28: Karolina | C28: Litwińska | D28: karolina.liwinska@zhp.net.pl | E28: +48 799196515 | F28: Strumień 58 | G28: Poland | H28: Zwiazek Harcerstwa Polskiego | I28: Strumień 58 | J28: 58 | K28: Łódź | L28: 14 | M28: 2 | N28: Friday | O28: 18:00 - 21:00 | P28: Monday | Q28: 09:00 - 12:00 | R28: 0 | S28: IST-17075 | T28: 375 | U28: Mollie | V28: 2025-02-16 21:27:46 | W28: 1739741266 | X28: Plus 1 to pay | Y28: 0 | Z28: 3
A29: 118 | B29: Maciej | C29: Rogowicz | D29: maciej.rogowicz@zhp.net.pl | E29: +48666677498 | F29: 0 | G29: Poland | H29: Zwiazek Harcerstwa Polskiego | I29: Nebula | J29: 141 | K29: Gdańsk | L29: 16 | M29: 1 | N29: Friday | O29: 15:00 - 18:00 | P29: Monday | Q29: 09:00 - 12:00 | R29: We wolud like to be togeter with 76 Silva, 74 Kotwice, 71A and 71N, plomienne zorze, venda vamos and diathus, if it is possible or at least partly together | S29: IST-19439 | T29: 425 | U29: Mollie | V29: 2025-02-23 18:49:46 | W29: 1740336586 | X29: 0 | Y29: 0 | Z29: 3
A30: 122 | B30: Julia | C30: Sało | D30: julia.salo@zhp.net.pl | E30: +48513504409 | F30: 0 | G30: Poland | H30: Zwiazek Harcerstwa Polskiego | I30: Feniksiątka | J30: 234 | K30: Warszawa | L30: 9 | M30: 2 | N30: Friday | O30: 15:00 - 18:00 | P30: Monday | Q30: 09:00 - 12:00 | R30: Our patrol is from one team with the Feniksiaki patrol (leader-Joanna Zubek). If it would be possible, we would appreciate being located at a common camping spot, as we will share tents and equipment. Likewise with activities-we will be grateful if our hikes and activities are scheduled on the same days. | S30: IST-17697 | T30: 275 | U30: Mollie | V30: 2025-02-23 20:21:28 | W30: 1740342088 | X30: 0 | Y30: 0 | Z30: 3
A31: 123 | B31: Dorota | C31: Kułaga | D31: dorota.kulaga@zhp.net.pl | E31: +48510454231 | F31: 0 | G31: Poland | H31: Zwiazek Harcerstwa Polskiego | I31: 74 GDH „Kotwice” | J31: 74 | K31: Gdańsk | L31: 8 | M31: 2 | N31: Friday | O31: 15:00 - 18:00 | P31: Monday | Q31: 09:00 - 12:00 | R31: If possible we would like to be togetger with all troops from Gdańsk or partly with them. (71A, 71N, 76 Silva, 141 Nebula, plomienne zorze, venda vamos, diathus) | S31: IST-31679 | T31: 250 | U31: Mollie | V31: 2025-02-23 20:30:09 | W31: 1740342609 | X31: 0 | Y31: 0 | Z31: 3
A32: 124 | B32: Aleksandra | C32: Mocarska | D32: aleksandra.mocarska@zhp.net.pl | E32: +48881202503 | F32: 0 | G32: Poland | H32: Zwiazek Harcerstwa Polskiego | I32: Dianthus | J32: 78 | K32: Gdańsk | L32: 8 | M32: 1 | N32: Friday | O32: 15:00 - 18:00 | P32: Monday | Q32: 09:00 - 12:00 | R32: If possible we would like to be together with 71A, 71N, 76 Silva, 74 Kotwice, 141 Nebula, plomienne zorze and venda vamos. Thank you! | S32: IST-10409 | T32: 225 | U32: Mollie | V32: 2025-02-23 20:34:23 | W32: 1740342863 | X32: 0 | Y32: 0 | Z32: 3
A33: 133 | B33: Joanna | C33: Zubek | D33: joanna.zubek@zhp.net.pl | E33: +48 534152804 | F33: 0 | G33: Poland | H33: Zwiazek Harcerstwa Polskiego | I33: Feniksiaki | J33: 234 | K33: Warszawa | L33: 10 | M33: 2 | N33: Friday | O33: 15:00 - 18:00 | P33: Monday | Q33: 09:00 - 12:00 | R33: Our patrol is from one team with the Feniksiątka patrol (leader-Julia Sało). If it would be possible, we would appreciate being located at a common camping spot, as we will share tents and equipment. Likewise with activities-we will be grateful if our hikes and activities are scheduled on the same days. | S33: IST | T33: 0 | U33: 0 | V33: 0 | W33: 0 | X33: 300 euro to be paid | Y33: 300 | Z33: 3
A34: 137 | B34: Stanisław | C34: Szymczykowski | D34: stanislaw.szymczykowski@zhp.net.pl | E34: +48 784118055 | F34: 0 | G34: Poland | H34: Zwiazek Harcerstwa Polskiego | I34: Błękitny Zenit | J34: 147 | K34: Warszawa | L34: 7 | M34: 2 | N34: Friday | O34: 15:00 - 18:00 | P34: Monday | Q34: 09:00 - 12:00 | R34: 0 | S34: 0 | T34: 0 | U34: 0 | V34: 0 | W34: 0 | X34: 225 euro to be paid | Y34: 225 | Z34: 3
A35: 138 | B35: Iga | C35: Woźniak | D35: iga.wozniak@zhp.net.pl | E35: +48 516061590 | F35: 0 | G35: Poland | H35: Zwiazek Harcerstwa Polskiego | I35: 94 GDSH ,,Venga, vamos!" | J35: 94 | K35: Gdańsk | L35: 7 | M35: 1 | N35: Friday | O35: 15:00 - 18:00 | P35: Monday | Q35: 09:00 - 12:00 | R35: 0 | S35: 0 | T35: 0 | U35: 0 | V35: 0 | W35: 0 | X35: 200 euro to be paid | Y35: 200 | Z35: 3
A36: 1 | B36: Arno | C36: Bottema | D36: arno@scoutingmeerhoven.nl | E36: +31622250254 | F36: 0 | G36: The Netherlands | H36: Scouting Nederland | I36: Sc.Burg.Welschen Meerhoven | J36: 3097 | K36: Eindhoven | L36: 36 | M36: 6 | N36: Friday | O36: 12:00 - 15:00 | P36: Monday | Q36: 12:00 - 15:00 | R36: 0 | S36: IST-90673 | T36: 1050 | U36: Mollie | V36: 2024-11-30 18:58:34 | W36: 1732993114 | X36: 0 | Y36: 0 | Z36: 3
A37: 10 | B37: Gun | C37: Holtackers | D37: gun@hubovra.nl | E37: +31622090428 | F37: 0 | G37: The Netherlands | H37: Scouting Nederland | I37: Scouting Hubovra | J37: 1452 | K37: Weert | L37: 22 | M37: 5 | N37: Friday | O37: 12:00 - 15:00 | P37: Monday | Q37: 12:00 - 15:00 | R37: 0 | S37: IST-10618 | T37: 675 | U37: Mollie | V37: 2024-11-30 19:50:43 | W37: 1732996243 | X37: 0 | Y37: 0 | Z37: 3
A38: 11 | B38: Doortje | C38: Tiedink | D38: Doortjetiedink1@icloud.com | E38: +31628184483 | F38: 0 | G38: The Netherlands | H38: Scouting Nederland | I38: Scouting Groessen | J38: 1271 | K38: Groessen | L38: 23 | M38: 5 | N38: Friday | O38: 12:00 - 15:00 | P38: Monday | Q38: 12:00 - 15:00 | R38: 0 | S38: IST-13152 | T38: 700 | U38: Mollie | V38: 2024-11-30 19:55:52 | W38: 1732996552 | X38: 0 | Y38: 0 | Z38: 3
A39: 14 | B39: Anniek | C39: van den Hurk | D39: scouts@sintstanislaus.nl | E39: +31611335004 | F39: 0 | G39: The Netherlands | H39: Scouting Nederland | I39: St. Stanislaus | J39: 1208 | K39: Culemborg | L39: 25 | M39: 5 | N39: Friday | O39: 12:00 - 15:00 | P39: Monday | Q39: 12:00 - 15:00 | R39: 0 | S39: IST-49187 | T39: 750 | U39: Mollie | V39: 2024-11-30 20:03:58 | W39: 1732997038 | X39: 0 | Y39: 0 | Z39: 3
A40: 15 | B40: Luuk | C40: Philipsen | D40: luukphilipsen8@gmail.com | E40: +31631525507 | F40: 0 | G40: The Netherlands | H40: Scouting Nederland | I40: Scoutinggroep de Meuleberg | J40: 1476 | K40: Blitterswijck | L40: 17 | M40: 4 | N40: Friday | O40: 12:00 - 15:00 | P40: Monday | Q40: 12:00 - 15:00 | R40: 0 | S40: IST-17335 | T40: 525 | U40: Mollie | V40: 2024-11-30 20:06:25 | W40: 1732997185 | X40: 0 | Y40: 0 | Z40: 3
A41: 55 | B41: Caspar | C41: Doornmalen | D41: casparvandoornmalen@gmail.com | E41: +31625431249 | F41: 0 | G41: The Netherlands | H41: Scouting Nederland | I41: Scouting St. Martinus | J41: 1606 | K41: Zaltbommel | L41: 10 | M41: 2 | N41: Friday | O41: 12:00 - 15:00 | P41: Monday | Q41: 12:00 - 15:00 | R41: 0 | S41: IST-18992 | T41: 300 | U41: Mollie | V41: 2024-12-20 13:06:03 | W41: 1734699963 | X41: 0 | Y41: 0 | Z41: 3
A42: 52 | B42: Randolph | C42: Caldwell | D42: scoutmastert21munich@gmail.com | E42: +491738714703 | F42: 0 | G42: United States | H42: Boy Scouts of America - Transatlantic Council | I42: Troop 21 | J42: 0021B | K42: Munich | L42: 12 | M42: 3 | N42: Friday | O42: 12:00 - 15:00 | P42: Monday | Q42: 09:00 - 12:00 | R42: 0 | S42: IST-47786 | T42: 375 | U42: Mollie | V42: 2024-12-13 14:58:14 | W42: 1734101894 | X42: 0 | Y42: 0 | Z42: 3
A43: 56 | B43: Daniel | C43: Cole | D43: daniel.cole32@live.com | E43: +12292510986 | F43: 0 | G43: United States | H43: Boy Scouts of America - Transatlantic Council | I43: Troop 12 | J43: 12 | K43: APO | L43: 35 | M43: 7 | N43: Friday | O43: 09:00 - 12:00 | P43: Monday | Q43: 12:00 - 15:00 | R43: 0 | S43: IST-13607 | T43: 1050 | U43: Mollie | V43: 2025-01-01 07:39:49 | W43: 1735717189 | X43: 0 | Y43: 0 | Z43: 3
A44: 79 | B44: Leah | C44: Gililland | D44: leahm2scott@gmail.com | E44: +49 | F44: 0 | G44: United States | H44: Boy Scouts of America - Transatlantic Council | I44: Troop 164 Sembach | J44: 164 | K44: Sembach | L44: 6 | M44: 2 | N44: Friday | O44: 15:00 - 18:00 | P44: Sunday | Q44: 09:00 - 12:00 | R44: 0 | S44: IST-89120 | T44: 200 | U44: Mollie | V44: 2025-02-01 14:15:40 | W44: 1738419340 | X44: 0 | Y44: 0 | Z44: 3
A45: 102 | B45: Aaron | C45: Hobbins | D45: aaron.hobbins@gmail.com | E45: +4915254780318 | F45: Mailing address: An den Hopfengaerten 1, 67722 Winnweiler | G45: United States | H45: Boy Scouts of America - Transatlantic Council | I45: Troop 69 Vogelweh | J45: T69B | K45: Kaiserslautern | L45: 6 | M45: 2 | N45: Friday | O45: 18:00 - 21:00 | P45: Sunday | Q45: 12:00 - 15:00 | R45: 0 | S45: IST-70602 | T45: 200 | U45: Mollie | V45: 2025-02-09 19:05:08 | W45: 1739127908 | X45: 0 | Y45: Additional request | Z45: 3
A46: 128 | B46: Robert | C46: Munson | D46: nebr_bob@hotmail.com | E46: +4915234636794 | F46: contact me for payment | G46: United States | H46: Boy Scouts of America - Transatlantic Council | I46: Troop | J46: 56 | K46: Bonn | L46: 9 | M46: 3 | N46: Friday | O46: 18:00 - 21:00 | P46: Monday | Q46: 09:00 - 12:00 | R46: We need the leaders to drive | S46: IST-12948 | T46: 300 | U46: Mollie | V46: 2025-03-09 15:56:31 | W46: 1741535792 | X46: 0 | Y46: 0 | Z46: 3
A47: 129 | B47: Kristin | C47: Heist | D47: kristin310@hotmail.com | E47: +32491994561 | F47: 0 | G47: United States | H47: Boy Scouts of America - Transatlantic Council | I47: Scouting America Troop 325G | J47: 325G | K47: SHAPE | L47: 12 | M47: 4 | N47: Friday | O47: 21:00 - 00:00 | P47: Monday | Q47: 09:00 - 12:00 | R47: Traveling extra adults due to travel from other locations. | S47: IST-51638 | T47: 400 | U47: Mollie | V47: 2025-03-18 18:43:11 | W47: 1742323392 | X47: 0 | Y47: 0 | Z47: 3
A48: 131 | B48: Chris | C48: Watts | D48: cbrannonwatts@gmail.com | E48: +18153120177 | F48: SHAPE BSA Troop 325B (the Boys' Troop) - please use my Belgian phone number for any correspondence +32 470 65 90 01, or my email: cbrannonwatts@gmail.com. | G48: United States | H48: Boy Scouts of America - Transatlantic Council | I48: SHAPE Troop 325B | J48: 325B | K48: SHAPE | L48: 12 | M48: 4 | N48: Friday | O48: 21:00 - 00:00 | P48: Monday | Q48: 09:00 - 12:00 | R48: If I have any cancellations or changes, who do I contact? I am not anticipating changes, but things do come up. | S48: IST-37418 | T48: 400 | U48: Mollie | V48: 2025-03-21 08:48:14 | W48: 1742546894 | X48: 0 | Y48: 0 | Z48: 3
L59: =SUM(L2:L50) -> 699 | M59: =SUM(M2:M50) -> 147 | N59: =L59+M59 -> 846

Sheet Subcamp 4
A1: No | B1: First name | C1: Last name | D1: Email | E1: Mobile phone | F1: Invoice details | G1: Country | H1: Scout Association | I1: Troop name | J1: Troop organisation number | K1: City | L1: Number of Children | M1: Number of Leaders | N1: Arrival day | O1: Arrival time | P1: Departure day | Q1: Departure time | R1: Further remarks (optional) | S1: Order Number | T1: Total Costs | U1: Payment Type | V1: Registration time | W1: Order Number2 | X1: Additional registrants | Y1: Comments RJ: | Z1: Subcamp
A2: {=_xlfn._xlws.FILTER('All Subcamps'!A2:Z139,'All Subcamps'!Z2:Z139=4)} -> 67 | B2: Šimon | C2: Trousil | D2: simon.trousil@seznam.cz | E2: +420720103492 | F2: 0 | G2: Czech Republic | H2: JUNAK - cesky skaut | I2: Orion Kladno | J2: 213.01 | K2: Kladno | L2: 18 | M2: 3 | N2: Friday | O2: 15:00 - 18:00 | P2: Monday | Q2: 09:00 - 12:00 | R2: We are traveling from the Czech Republic by bus together with another group of scouts and we are currently planning the bus, so we don't know the exact time of arrival. | S2: IST-92152 | T2: 525 | U2: Mollie | V2: 2025-01-24 10:58:50 | W2: 1737716330 | X2: 0 | Y2: 0 | Z2: 4
A3: 72 | B3: Vanda | C3: Hegerová | D3: vanda.hegerova@seznam.cz | E3: +420 | F3: 0 | G3: Czech Republic | H3: JUNAK - cesky skaut | I3: Blaník | J3: 114.07 | K3: Prague | L3: 4 | M3: 1 | N3: Friday | O3: 15:00 - 18:00 | P3: Monday | Q3: 09:00 - 12:00 | R3: Arrival time is not exactly we are still planing. | S3: IST-81258 | T3: 125 | U3: Mollie | V3: 2025-01-28 19:14:48 | W3: 1738091688 | X3: 0 | Y3: 0 | Z3: 4
A4: 76 | B4: Vlastimil | C4: Buriánek | D4: vlastimil.burianek@skaut.cz | E4: +420725561858 | F4: 0 | G4: Czech Republic | H4: JUNAK - cesky skaut | I4: Děti přírody | J4: 713.02 | K4: Prostějov | L4: 9 | M4: 2 | N4: Friday | O4: 15:00 - 18:00 | P4: Monday | Q4: 12:00 - 15:00 | R4: Departure/arrival times are (still) approximate. | S4: IST-20023 | T4: 275 | U4: Mollie | V4: 2025-01-31 20:17:50 | W4: 1738354670 | X4: 0 | Y4: 0 | Z4: 4
A5: 82 | B5: Lucie | C5: Urbanová | D5: lucie.urbn@gmail.com | E5: +420728900846 | F5: 0 | G5: Czech Republic | H5: JUNAK - cesky skaut | I5: Devítky | J5: 533.02 | K5: Litomyšl | L5: 8 | M5: 1 | N5: Friday | O5: 12:00 - 15:00 | P5: Monday | Q5: 12:00 - 15:00 | R5: 0 | S5: IST-66761 | T5: 225 | U5: Mollie | V5: 2025-02-03 15:13:33 | W5: 1738595613 | X5: 0 | Y5: 0 | Z5: 4
A6: 85 | B6: Jiří | C6: Nevřivý | D6: nevrivy.skaut@gmail.com | E6: +420736678622 | F6: 0 | G6: Czech Republic | H6: JUNAK - cesky skaut | I6: Artemis/Ontario | J6: 724.06 | K6: Zlín-Malenovice | L6: 20 | M6: 4 | N6: Friday | O6: 15:00 - 18:00 | P6: Monday | Q6: 09:00 - 12:00 | R6: 0 | S6: IST-97908 | T6: 600 | U6: Mollie | V6: 2025-02-04 22:26:15 | W6: 1738707976 | X6: 0 | Y6: 0 | Z6: 4
A7: 101 | B7: Martin | C7: Matyáš | D7: matyasmartin0@gmail.com | E7: +420608642615 | F7: 0 | G7: Czech Republic | H7: JUNAK - cesky skaut | I7: Tumulus Újezd u Brna aneb děcka, pecka, pojedeme do Německa | J7: 623.14 | K7: Újezd u Brna | L7: 5 | M7: 1 | N7: Friday | O7: 15:00 - 18:00 | P7: Monday | Q7: 12:00 - 15:00 | R7: 0 | S7: IST-30049 | T7: 150 | U7: Mollie | V7: 2025-02-09 18:29:12 | W7: 1739125752 | X7: 0 | Y7: 0 | Z7: 4
A8: 127 | B8: Marie Anna | C8: Chlachulová | D8: mchlachulov.a@seznam.cz | E8: +420773883110 | F8: 0 | G8: Czech Republic | H8: JUNAK - cesky skaut | I8: Mustangové | J8: 722.01 | K8: Uherské Hradiště | L8: 8 | M8: 2 | N8: Friday | O8: 15:00 - 18:00 | P8: Monday | Q8: 09:00 - 12:00 | R8: We have 2 leaders And 8 children, since we have both just turned 18 And we have no previous experience travelling with kids alone, we think it will be more responsible and safer to travel abroad with the kids with 2 leaders . | S8: IST-81116 | T8: 250 | U8: Mollie | V8: 2025-03-04 16:42:05 | W8: 1741106525 | X8: 0 | Y8: 0 | Z8: 4
A9: 19 | B9: Caroline | C9: Pintsch | D9: caroline@pintsch.de | E9: +4915786783461 | F9: 0 | G9: Germany | H9: Deutsche Pfadfinderschaft Sankt Georg | I9: DPSG Stamm Alzenau | J9: 2020329 | K9: Alzenau | L9: 17 | M9: 4 | N9: Friday | O9: 15:00 - 18:00 | P9: Monday | Q9: 12:00 - 15:00 | R9: 0 | S9: IST-23477 | T9: 525 | U9: Mollie | V9: 2024-11-30 23:13:25 | W9: 1733008405 | X9: 0 | Y9: 0 | Z9: 4
A10: 40 | B10: Anna-Maria | C10: Aggelakos | D10: anna.aggelakos@hotmail.de | E10: +491722940241 | F10: Empfänger: Freundes- u. Förderverein des Stammes Sr. Felicitas HD-Zgh e.V. IBAN: DE28 6709 2300 0033 1350 92 BIC: GENODE61WNM Bank: Volksbank Kurpfalz eG | G10: Germany | H10: Deutsche Pfadfinderschaft Sankt Georg | I10: Stamm Schwester Felicitas Ziegelhausen | J10: DPSG Schwester Felicitas Ziegelhausen | K10: Heidelberg | L10: 12 | M10: 3 | N10: Friday | O10: 15:00 - 18:00 | P10: Monday | Q10: 12:00 - 15:00 | R10: 0 | S10: IST-12782 | T10: 375 | U10: Mollie | V10: 2024-12-02 22:20:06 | W10: 1733178006 | X10: 0 | Y10: 0 | Z10: 4
A11: 41 | B11: Wolfgang | C11: Otto | D11: scouterwolfgang@aol.com | E11: +4915753131324 | F11: 0 | G11: Germany | H11: Deutsche Pfadfinderschaft Sankt Georg | I11: DPSG Moers St. Josef | J11: 14/08/01 | K11: Moers | L11: 5 | M11: 1 | N11: Friday | O11: 18:00 - 21:00 | P11: Monday | Q11: 09:00 - 12:00 | R11: 0 | S11: IST-80873 | T11: 150 | U11: Mollie | V11: 2024-12-03 22:28:03 | W11: 1733264883 | X11: 0 | Y11: 0 | Z11: 4
A12: 45 | B12: Robert | C12: Birkmann | D12: robert.birkmann@ostgoten.de | E12: +4915151277360 | F12: 0 | G12: Germany | H12: Deutsche Pfadfinderschaft Sankt Georg | I12: Stamm Ostgoten/Rheinbezirk | J12: 010107 | K12: Krefeld | L12: 21 | M12: 5 | N12: Friday | O12: 09:00 - 12:00 | P12: Monday | Q12: 09:00 - 12:00 | R12: 0 | S12: IST-12385 | T12: 650 | U12: Mollie | V12: 2024-12-07 20:10:04 | W12: 1733602204 | X12: 0 | Y12: 0 | Z12: 4
A13: 47 | B13: Wolfgang | C13: Otto | D13: scouterwolfgang@aol.com | E13: +4915753131324 | F13: 0 | G13: Germany | H13: Deutsche Pfadfinderschaft Sankt Georg | I13: DPSG Moers St. Josef | J13: 14/08/01 | K13: Moers | L13: 1 | M13: 1 | N13: Friday | O13: 15:00 - 18:00 | P13: Monday | Q13: 09:00 - 12:00 | R13: 0 | S13: IST-61800 | T13: 50 | U13: Mollie | V13: 2024-12-07 20:57:29 | W13: 1733605049 | X13: 0 | Y13: 0 | Z13: 4
A14: 111 | B14: Wolfgang | C14: Otto | D14: scouterwolfgang@aol.com | E14: +4915753131324 | F14: 0 | G14: Germany | H14: Deutsche Pfadfinderschaft Sankt Georg | I14: DPSG Moers St. Josef | J14: 14/08/01 | K14: Moers | L14: 17 | M14: 3 | N14: Friday | O14: 18:00 - 21:00 | P14: Monday | Q14: 09:00 - 12:00 | R14: Our Trailer is part of our kitchen. So it has to sty on our campsite! | S14: IST-21261 | T14: 500 | U14: Mollie | V14: 2025-02-17 01:00:14 | W14: 1739754014 | X14: 0 | Y14: 0 | Z14: 4
A15: 86 | B15: Karolina | C15: Pazdro | D15: karolina.pazdro@zhp.net.pl | E15: +48609724261 | F15: 0 | G15: Poland | H15: Zwiazek Harcerstwa Polskiego | I15: Brzęczące Chrabąszcze | J15: 16 | K15: Kraków | L15: 5 | M15: 1 | N15: Friday | O15: 15:00 - 18:00 | P15: Monday | Q15: 09:00 - 12:00 | R15: 0 | S15: IST-12955 | T15: 150 | U15: Mollie | V15: 2025-02-05 12:07:35 | W15: 1738757255 | X15: 0 | Y15: 0 | Z15: 4
A16: 87 | B16: Magdalena | C16: Szymczak | D16: szymczak.magdalena@zhp.net.pl | E16: +48786087728 | F16: 0 | G16: Poland | H16: Zwiazek Harcerstwa Polskiego | I16: Łosie z Górnej półki | J16: 222 | K16: Łódź | L16: 13 | M16: 2 | N16: Friday | O16: 18:00 - 21:00 | P16: Monday | Q16: 09:00 - 12:00 | R16: 0 | S16: IST-22412 | T16: 375 | U16: Mollie | V16: 2025-02-05 12:18:04 | W16: 1738757884 | X16: 0 | Y16: 0 | Z16: 4
A17: 88 | B17: Natalia | C17: Gwizd | D17: natalia.gwizd@zhp.net.pl | E17: +48607781951 | F17: 0 | G17: Poland | H17: Zwiazek Harcerstwa Polskiego | I17: Polish Eagles | J17: 882 | K17: Łódź | L17: 15 | M17: 2 | N17: Friday | O17: 18:00 - 21:00 | P17: Monday | Q17: 09:00 - 12:00 | R17: 0 | S17: IST-10548 | T17: 425 | U17: Mollie | V17: 2025-02-05 12:21:04 | W17: 1738758064 | X17: 0 | Y17: 0 | Z17: 4
A18: 89 | B18: Natasza | C18: Pytlarczyk | D18: natasza.pytlarczyk@zhp.net.pl | E18: +48792891243 | F18: 0 | G18: Poland | H18: Zwiazek Harcerstwa Polskiego | I18: bunt | J18: 32 | K18: Warszawa Praga-Południe | L18: 8 | M18: 2 | N18: Friday | O18: 18:00 - 21:00 | P18: Monday | Q18: 09:00 - 12:00 | R18: 0 | S18: IST-31219 | T18: 250 | U18: Mollie | V18: 2025-02-05 12:32:31 | W18: 1738758751 | X18: 0 | Y18: 0 | Z18: 4
A19: 134 | B19: Pola | C19: Drygiel | D19: pola.drygiel@zhp.pl | E19: +48 602497212 | F19: 0 | G19: Poland | H19: Zwiazek Harcerstwa Polskiego | I19: Kociaki górą | J19: 211 | K19: warszawa | L19: 9 | M19: 2 | N19: Friday | O19: 15:00 - 18:00 | P19: Monday | Q19: 09:00 - 12:00 | R19: 0 | S19: 0 | T19: 0 | U19: 0 | V19: 0 | W19: 0 | X19: 275 euro to be paid | Y19: 275 | Z19: 4
A20: 135 | B20: Sabina | C20: Gurowiec | D20: sabina.gurowiec@zhp.net.pl | E20: +48 509632613 | F20: 0 | G20: Poland | H20: Zwiazek Harcerstwa Polskiego | I20: 16 Drużyna Harcerska Tarnowskie Góry | J20: 16 | K20: Tarnowskie Góry | L20: 15 | M20: 2 | N20: Friday | O20: 15:00 - 18:00 | P20: Monday | Q20: 09:00 - 12:00 | R20: 0 | S20: 0 | T20: 0 | U20: 0 | V20: 0 | W20: 0 | X20: 425 euro to be paid | Y20: 425 | Z20: 4
A21: 5 | B21: Bob | C21: Lelieveld | D21: boblelieveld@gmail.com | E21: +31627145802 | F21: 0 | G21: The Netherlands | H21: Scouting Nederland | I21: Scouting Uotha | J21: 1737 | K21: Uden | L21: 32 | M21: 4 | N21: Friday | O21: 12:00 - 15:00 | P21: Monday | Q21: 12:00 - 15:00 | R21: 0 | S21: IST-11233 | T21: 900 | U21: Mollie | V21: 2024-11-30 19:30:16 | W21: 1732995016 | X21: 0 | Y21: 0 | Z21: 4
A22: 6 | B22: Juriaan | C22: Adams | D22: juriaan.adams@scoutingamby.nl | E22: +31621685513 | F22: 0 | G22: The Netherlands | H22: Scouting Nederland | I22: Intercamp Nederland | J22: 9133 | K22: Sittard | L22: 7 | M22: 4 | N22: Friday | O22: 12:00 - 15:00 | P22: Monday | Q22: 12:00 - 15:00 | R22: Special need Group - part of Moppertjesmeute - no accessible Dixi needed ( Didi confirmed) | S22: IST-70768 | T22: 275 | U22: Mollie | V22: 2024-11-30 19:38:53 | W22: 1732995533 | X22: 0 | Y22: 0 | Z22: 4
A23: 7 | B23: Eric-Jan | C23: Grondstra | D23: e.j.grondstra@gmail.com | E23: +31621504255 | F23: 0 | G23: The Netherlands | H23: Scouting Nederland | I23: Scouting Polaris | J23: 129776 | K23: Heereveen | L23: 19 | M23: 5 | N23: Friday | O23: 12:00 - 15:00 | P23: Monday | Q23: 12:00 - 15:00 | R23: 0 | S23: IST-19148 | T23: 600 | U23: Mollie | V23: 2024-11-30 19:42:53 | W23: 1732995773 | X23: 0 | Y23: 0 | Z23: 4
A24: 48 | B24: Erik | C24: Iliff | D24: iliffe410@gmail.com | E24: +31621692799 | F24: 0 | G24: United States | H24: Boy Scouts of America - Transatlantic Council | I24: Troop 100 | J24: 100 | K24: Brunssum | L24: 1 | M24: 1 | N24: Friday | O24: 18:00 - 21:00 | P24: Monday | Q24: 09:00 - 12:00 | R24: 0 | S24: IST-13942 | T24: 75 | U24: Mollie | V24: 2024-12-07 21:02:55 | W24: 1733605375 | X24: 0 | Y24: 0 | Z24: 4
A25: 68 | B25: Roberto | C25: Baltazar | D25: bltzrr@gmail.com | E25: +4915117534988 | F25: 0 | G25: United States | H25: Boy Scouts of America - Transatlantic Council | I25: Atomic Tacos | J25: 156 Ramstien | K25: Ramstein Air Base | L25: 20 | M25: 8 | N25: Friday | O25: 18:00 - 21:00 | P25: Monday | Q25: 09:00 - 12:00 | R25: 0 | S25: IST-12821 | T25: 700 | U25: Mollie | V25: 2025-01-24 13:58:18 | W25: 1737727098 | X25: 0 | Y25: 0 | Z25: 4
A26: 69 | B26: Amy | C26: Hielen | D26: amyhielen@gmail.com | E26: +491607073891 | F26: 0 | G26: United States | H26: Boy Scouts of America - Transatlantic Council | I26: Troop | J26: 43 and 86 | K26: Oberusal | L26: 5 | M26: 4 | N26: Friday | O26: 18:00 - 21:00 | P26: Monday | Q26: 09:00 - 12:00 | R26: We may want to add more kids to the registration. | S26: IST-14176 | T26: 225 | U26: Mollie | V26: 2025-01-25 14:54:13 | W26: 1737816854 | X26: 0 | Y26: Requested to register additional participants | Z26: 4
A27: 74 | B27: Patrick | C27: Stevens | D27: pmstevensv@icloud.com | E27: +31625066599 | F27: 0 | G27: United States | H27: Boy Scouts of America - Transatlantic Council | I27: Troop 100 | J27: 100 | K27: Brunssum | L27: 17 | M27: 7 | N27: Friday | O27: 18:00 - 21:00 | P27: Monday | Q27: 09:00 - 12:00 | R27: Our troop signup consists of both a boys’ troop and a girls’ troop (Troop 100B and Troop 100G), requiring at least one registered female leader to be present at all times per BSA Youth Protection policies. With only two female leaders available, additional adult coverage is necessary to ensure compliance while allowing for flexibility in activities. With 17 scouts attending, the standard 1:5 ratio would suggest a minimum of four leaders, but this does not account for the logistical complexities of managing both the boys’ and girls’ troops. Also, transportation logistics necessitate additional adults, requiring more leaders to transport all participants to and from the campout. | S27: IST-16807 | T27: 600 | U27: Mollie | V27: 2025-01-30 18:15:03 | W27: 1738260903 | X27: 0 | Y27: 0 | Z27: 4
L35: =SUM(L2:L28) -> 311 | M35: =SUM(M2:M28) -> 75 | N35: =L35+M35 -> 386

Sheet Sheet2
A1: 8 | B1: 1
A2: 7 | B2: 1
A3: 16 | B3: 1
A4: 8 | B4: 2
A5: 8 | B5: 1
A6: 7 | B6: 2
A7: 13 | B7: 1
A9: =SUM(A1:A7) -> 67 | B9: =SUM(B1:B7) -> 9 | C9: =SUM(A9:B9) -> 76

Sheet  Nations
B3: Rijlabels | C3: Som van Number of Children | D3: Som van Number of Leaders | E3: Cildren | F3: Leaders | G3: Total | H3: Contingent sizes | J3: Delta
B4: Belgium | C4: 27 | D4: 8 | E4: =SUMIF('All Subcamps'!$G:$G,' Nations'!$B4,'All Subcamps'!$L:$L) -> 27 | F4: =SUMIF('All Subcamps'!$G:$G,' Nations'!$B4,'All Subcamps'!$M:$M) -> 8 | G4: =SUM(E4:F4) -> 35 | H4: 40 | J4: =H4-G4 -> 5 | L4: =G4/4 -> 8.75
B5: Czech Republic | C5: 400 | D5: 80 | E5: =SUMIF('All Subcamps'!$G:$G,' Nations'!$B5,'All Subcamps'!$L:$L) -> 400 | F5: =SUMIF('All Subcamps'!$G:$G,' Nations'!$B5,'All Subcamps'!$M:$M) -> 80 | G5: =SUM(E5:F5) -> 480 | H5: 480 | J5: =H5-G5 -> 0 | L5: =G5/4 -> 120
B6: France | C6: 32 | D6: 8 | E6: =SUMIF('All Subcamps'!$G:$G,' Nations'!$B6,'All Subcamps'!$L:$L) -> 21 | F6: =SUMIF('All Subcamps'!$G:$G,' Nations'!$B6,'All Subcamps'!$M:$M) -> 4 | G6: =SUM(E6:F6) -> 25 | H6: 40 | J6: =H6-G6 -> 15 | L6: =G6/4 -> 6.25
B7: Germany | C7: 373 | D7: 87 | E7: =SUMIF('All Subcamps'!$G:$G,' Nations'!$B7,'All Subcamps'!$L:$L) -> 376 | F7: =SUMIF('All Subcamps'!$G:$G,' Nations'!$B7,'All Subcamps'!$M:$M) -> 87 | G7: =SUM(E7:F7) -> 463 | H7: 480 | J7: =H7-G7 -> 17 | L7: =G7/4 -> 115.75
B8: Guests | C8: 125 | D8: 30 | E8: =SUMIF('All Subcamps'!$G:$G,' Nations'!$B8,'All Subcamps'!$L:$L) -> 0 | F8: =SUMIF('All Subcamps'!$G:$G,' Nations'!$B8,'All Subcamps'!$M:$M) -> 0 | G8: =SUM(E8:F8) -> 0 | H8: 100 | J8: =H8-G8 -> 100 | L8: =G8/4 -> 0
B9: Poland | C9: 396 | D9: 62 | E9: =SUMIF('All Subcamps'!$G:$G,' Nations'!$B9,'All Subcamps'!$L:$L) -> 396 | F9: =SUMIF('All Subcamps'!$G:$G,' Nations'!$B9,'All Subcamps'!$M:$M) -> 62 | G9: =SUM(E9:F9) -> 458 | H9: 480 | J9: =H9-G9 -> 22 | L9: =G9/4 -> 114.5
B10: The Netherlands | C10: 377 | D10: 83 | E10: =SUMIF('All Subcamps'!$G:$G,' Nations'!$B10,'All Subcamps'!$L:$L) -> 377 | F10: =SUMIF('All Subcamps'!$G:$G,' Nations'!$B10,'All Subcamps'!$M:$M) -> 83 | G10: =SUM(E10:F10) -> 460 | H10: 480 | J10: =H10-G10 -> 20 | L10: =G10/4 -> 115
B11: United States | C11: 290 | D11: 88 | E11: =SUMIF('All Subcamps'!$G:$G,' Nations'!$B11,'All Subcamps'!$L:$L) -> 280 | F11: =SUMIF('All Subcamps'!$G:$G,' Nations'!$B11,'All Subcamps'!$M:$M) -> 85 | G11: =SUM(E11:F11) -> 365 | H11: 450 | J11: =H11-G11 -> 85 | L11: =G11/4 -> 91.25
B12: Eindtotaal | C12: 2020 | D12: 446 | H12: =SUM(H4:H11) -> 2550 | J12: =SUM(J4:J11) -> 264 | L12: =G12/4 -> 0
J13: =J12*25 -> 6600
B14: GB | E14: =SUMIF('All Subcamps'!$G:$G,' Nations'!$B14,'All Subcamps'!$L:$L) -> 63 | F14: =SUMIF('All Subcamps'!$G:$G,' Nations'!$B14,'All Subcamps'!$M:$M) -> 17 | G14: =SUM(E14:F14) -> 80 | L14: =G14/4 -> 20
B15: Luxembourg | E15: =SUMIF('All Subcamps'!$G:$G,' Nations'!$B15,'All Subcamps'!$L:$L) -> 30 | F15: =SUMIF('All Subcamps'!$G:$G,' Nations'!$B15,'All Subcamps'!$M:$M) -> 5 | G15: =SUM(E15:F15) -> 35 | L15: =G15/4 -> 8.75
B16: Hungary | E16: =SUMIF('All Subcamps'!$G:$G,' Nations'!$B16,'All Subcamps'!$L:$L) -> 12 | F16: =SUMIF('All Subcamps'!$G:$G,' Nations'!$B16,'All Subcamps'!$M:$M) -> 5 | G16: =SUM(E16:F16) -> 17 | L16: =G16/4 -> 4.25
B17: Slovakia | E17: =SUMIF('All Subcamps'!$G:$G,' Nations'!$B17,'All Subcamps'!$L:$L) -> 7 | F17: =SUMIF('All Subcamps'!$G:$G,' Nations'!$B17,'All Subcamps'!$M:$M) -> 2 | G17: =SUM(E17:F17) -> 9 | L17: =G17/4 -> 2.25
E20: =SUM(E4:E17) -> 1989 | F20: =SUM(F4:F17) -> 438 | G20: =SUM(G4:G17) -> 2427

Sheet Subcamp calculation
A2: Subcamp | B2: Space | C2: Qm | D2: People
A3: 1 | B3: 4030 | C3: =B3/$C$7 -> 349.93953 | D3: ='Subcamp 1'!N31 -> 358
A4: 2 | B4: 9680 | C4: =B4/$C$7 -> 840.54955 | D4: ='Subcamp 2'!N58 -> 837
A5: 3 | B5: 9880 | C5: =B5/$C$7 -> 857.91628 | D5: ='Subcamp 3'!N59 -> 846
A6: 4 | B6: 4360 | C6: =B6/$C$7 -> 378.59463 | D6: ='Subcamp 4'!N35 -> 386
B7: =SUM(B3:B6) -> 27950 | C7: =B7/' Nations'!G20 -> 11.516275 | D7: =SUM(D3:D6) -> 2427 | E7: =SUM(C3:C6) -> 2427
